Workbook
Name отбор: OFFSET(#REF!,0,0,MAX(#REF!),1)
Name отбор: OFFSET(#REF!,0,0,MAX(#REF!),1)
Name отбор: OFFSET(#REF!,0,0,MAX(#REF!),1)
Name отбор: OFFSET(#REF!,0,0,MAX(#REF!),1)
Name отбор: OFFSET(#REF!,0,0,MAX(#REF!),1)
Name отбор: OFFSET(#REF!,0,0,MAX(#REF!),1)
Name отбор: OFFSET(#REF!,0,0,MAX(#REF!),1)
Name отбор: OFFSET(#REF!,0,0,MAX(#REF!),1)
Name отбор: OFFSET(#REF!,0,0,MAX(#REF!),1)
Name отбор: OFFSET(#REF!,0,0,MAX(#REF!),1)
Name отбор: OFFSET(#REF!,0,0,MAX(#REF!),1)
Name отбор: OFFSET(#REF!,0,0,MAX(#REF!),1)
Name отбор: OFFSET(#REF!,0,0,MAX(#REF!),1)
Name отбор: OFFSET(#REF!,0,0,MAX(#REF!),1)
Name отбор: OFFSET(#REF!,0,0,MAX(#REF!),1)
Name отбор: OFFSET(#REF!,0,0,MAX(#REF!),1)
Name отбор: OFFSET(#REF!,0,0,MAX(#REF!),1)
Name отбор: OFFSET(#REF!,0,0,MAX(#REF!),1)
Name отбор: OFFSET(#REF!,0,0,MAX(#REF!),1)
Name отбор: OFFSET(#REF!,0,0,MAX(#REF!),1)
Name отбор: OFFSET(#REF!,0,0,MAX(#REF!),1)
Name отбор: OFFSET(#REF!,0,0,MAX(#REF!),1)
Name отбор: OFFSET(#REF!,0,0,MAX(#REF!),1)
Name отбор: OFFSET(#REF!,0,0,MAX(#REF!),1)
Name отбор: OFFSET(#REF!,0,0,MAX(#REF!),1)
Name отбор: OFFSET(#REF!,0,0,MAX(#REF!),1)
Name отбор: OFFSET(#REF!,0,0,MAX(#REF!),1)
Name отбор: OFFSET(#REF!,0,0,MAX(#REF!),1)
Name отбор: OFFSET(#REF!,0,0,MAX(#REF!),1)
Name отбор: OFFSET(#REF!,0,0,MAX(#REF!),1)
Name отбор: OFFSET(#REF!,0,0,MAX(#REF!),1)
Name отбор: OFFSET(#REF!,0,0,MAX(#REF!),1)
Name отбор: OFFSET(#REF!,0,0,MAX(#REF!),1)
Name отбор: OFFSET(#REF!,0,0,MAX(#REF!),1)
Name отбор: OFFSET(#REF!,0,0,MAX(#REF!),1)
Name отбор: OFFSET(#REF!,0,0,MAX(#REF!),1)
Name Приоритеты: OFFSET(#REF!,0,0,MAX(#REF!),1)
Name Приоритеты: OFFSET(#REF!,0,0,MAX(#REF!),1)
Name Приоритеты: OFFSET(#REF!,0,0,MAX(#REF!),1)
Name Приоритеты: OFFSET(#REF!,0,0,MAX(#REF!),1)
Name Приоритеты: OFFSET(#REF!,0,0,MAX(#REF!),1)
Name Приоритеты: OFFSET(#REF!,0,0,MAX(#REF!),1)
Name Приоритеты: OFFSET(#REF!,0,0,MAX(#REF!),1)
Name Приоритеты: OFFSET(#REF!,0,0,MAX(#REF!),1)
Name Приоритеты: OFFSET(#REF!,0,0,MAX(#REF!),1)
Name Приоритеты: OFFSET(#REF!,0,0,MAX(#REF!),1)
Name Приоритеты: OFFSET(#REF!,0,0,MAX(#REF!),1)
Name Приоритеты: OFFSET(#REF!,0,0,MAX(#REF!),1)
Name Приоритеты: OFFSET(#REF!,0,0,MAX(#REF!),1)
Name Приоритеты: OFFSET(#REF!,0,0,MAX(#REF!),1)
Name Приоритеты: OFFSET(#REF!,0,0,MAX(#REF!),1)
Name Приоритеты: OFFSET(#REF!,0,0,MAX(#REF!),1)
Name Приоритеты: OFFSET(#REF!,0,0,MAX(#REF!),1)
Name Приоритеты: OFFSET(#REF!,0,0,MAX(#REF!),1)
Name Приоритеты: OFFSET(#REF!,0,0,MAX(#REF!),1)
Name Приоритеты: OFFSET(#REF!,0,0,MAX(#REF!),1)
Name Приоритеты: OFFSET(#REF!,0,0,MAX(#REF!),1)
Name Приоритеты: OFFSET(#REF!,0,0,MAX(#REF!),1)
Name Приоритеты: OFFSET(#REF!,0,0,MAX(#REF!),1)
Name Приоритеты: OFFSET(#REF!,0,0,MAX(#REF!),1)

Sheet Форма
A1: Анкета проведения экспертизы проекта КПМ
A2: Номер проекта из "Системы Экспертиз" | C2: КПМ-0244
A3: Наименование тематики | C3: Определение критериев профпригодности в условиях воздействия вредных производственных факторов работников, перенесших новую коронавирусную инфекцию (COVID-19)
A4: Код-шифр тематики | C4: FGFE-2023-0008
A5: Наименование учреждения | C5: Федеральное государственное бюджетное научное учреждение "Научно-исследовательский институт медицины труда имени академика Н.Ф.Измерова"
A6: Год начала проекта | C6: 2023
A7: Год окончания проекта | C7: 2025
A8: Оценка результатов научно-исследовательских работ
A9: № | B9: Определите, к какому виду относится достигнутый результат НИР, возможен выбор (выбрать результат из выпадающего списка) | C9: Определите, к какому типу относится достигнутый результат НИР (выбрать тип результата из выпадающего списка) | D9: Отметьте приоритетную проблему медицины и здравоохранении и отметьте вклад результата в ее решение (перейти по ссылке на форму) | E9: Отметьте все задачи, полностью решенные к моменту завершения НИР или данного этапа НИР в рамках достижения УГТ оцениваемого научного результата (перейти по ссылке на форму) | F9: Отметьте все информационные материалы, которые, по Вашей оценке, имеются в отчетной документации о результатах НИР (перейти по ссылке на форму) | G9: Определите, к каким критическим технологиям, отмеченным в указе Президента Российской Федерации от 18 июня 2024 года № 529 "Об утверждении приоритетных направлений научно-технологического развития и перечня важнейших наукоемких технологий" относится результат НИР (перейти по ссылке на форму) | H9: Определите, к каким сквозным технологиям, отмеченным в указе Президента Российской Федерации от 18 июня 2024 года № 529 "Об утверждении приоритетных направлений научно-технологического развития и перечня важнейших наукоемких технологий" относится результат НИР (перейти по ссылке на форму) | I9: Для проектов завершенных в 2024 году Определите, могут ли научные результаты, полученные при выполнении научно-исследовательской работы, при наличии финансирования стать основой для последующих НИОКТР (перейти по ссылке на форму) | J9: Для проектов завершенных в 2024 году Определите результаты, которые могут быть достигнуты в интервал 2026-2030 гг. (перейти по ссылке на форму) | K9: Определите, соответствует ли достигнутый научный результат НИР тем ожидаемым результатам, которые указаны в проекте тематики научного исследования | L9: Общий вывод
A10: 1 | B10: Метод профилактики | C10: Клинические рекомендации | D10: =IF(OR(B10=O10,C10=O10),"",HYPERLINK("#Р1!A6","переход на форму")) -> переход на форму | E10: =IF(OR(B10=O10,C10=O10),"",IF(C10="Лекарственный препарат",HYPERLINK("#Р1_УГТ_ЛП!A6","переход на форму"),IF(C10="Медицинское изделие",HYPERLINK("#Р1_УГТ_МИ!A6","переход на форму"),IF(C10="Клинические рекомендации",HYPERLINK("#Р1_УГТ_КР!A6","переход на форму"),IF(C10="Иное",HYPERLINK("#Р1_УГТ_Иное!A6","переход на форму"),""))))) -> переход на форму | F10: =IF(OR(B10=O10,C10=O10),"",IF(C10="Лекарственный препарат",HYPERLINK("#Р1_ДОК_ЛП!A6","переход на форму"),IF(C10="Медицинское изделие",HYPERLINK("#Р1_ДОК_МИ!A6","переход на форму"),IF(C10="Клинические рекомендации",HYPERLINK("#Р1_ДОК_КР!A6","переход на форму"),IF(C10="Иное",HYPERLINK("#Р1_ДОК_Иное!A6","переход на форму"),""))))) -> переход на форму | G10: =IF(OR(B10=O10,C10=O10),"",HYPERLINK("#Р1_КТ!A6","переход на форму")) -> переход на форму | H10: =IF(OR(B10=O10,C10=O10),"",HYPERLINK("#Р1_СТ!A6","переход на форму")) -> переход на форму | I10: =IF(OR(B10=O10,C10=O10,C7<>2024),"",HYPERLINK("#Р1_НИОКТР_1!A6","переход на форму")) | J10: =IF(OR(B10=O10,C10=O10,C7<>2024,Р1_НИОКТР_1!E7<140),"",HYPERLINK("#Р1_НИОКТР_2!A6","переход на форму")) | K10: Соответствует | L10: Проводится формирование базы данных работников «шумовых» профессий, перенесших COVID-19, для оценки влияния вирусной нагрузки на сроки формирования нейросенсорной тугоухости в условиях воздействия производственного шума.
A11: 2 | B11: Метод диагностики | C11: Клинические рекомендации | D11: =IF(OR(B11=O11,C11=O11),"",HYPERLINK("#Р2!A6","переход на форму")) -> переход на форму | E11: =IF(OR(B11=O11,C11=O11),"",IF(C11="Лекарственный препарат",HYPERLINK("#Р2_УГТ_ЛП!A6","переход на форму"),IF(C11="Медицинское изделие",HYPERLINK("#Р2_УГТ_МИ!A6","переход на форму"),IF(C11="Клинические рекомендации",HYPERLINK("#Р2_УГТ_КР!A6","переход на форму"),IF(C11="Иное",HYPERLINK("#Р2_УГТ_Иное!A6","переход на форму"),""))))) -> переход на форму | F11: =IF(OR(B11=O11,C11=O11),"",IF(C11="Лекарственный препарат",HYPERLINK("#Р2_ДОК_ЛП!A6","переход на форму"),IF(C11="Медицинское изделие",HYPERLINK("#Р2_ДОК_МИ!A6","переход на форму"),IF(C11="Клинические рекомендации",HYPERLINK("#Р2_ДОК_КР!A6","переход на форму"),IF(C11="Иное",HYPERLINK("#Р2_ДОК_Иное!A6","переход на форму"),""))))) -> переход на форму | G11: =IF(OR(B11=O11,C11=O11),"",HYPERLINK("#Р2_КТ!A6","переход на форму")) -> переход на форму | H11: =IF(OR(B11=O11,C11=O11),"",HYPERLINK("#Р2_СТ!A6","переход на форму")) -> переход на форму | I11: =IF(OR(B11=O11,C11=O11,C7<>2024),"",HYPERLINK("#Р2_НИОКТР_1!A6","переход на форму")) | J11: =IF(OR(B11=O11,C11=O11,C7<>2024,Р2_НИОКТР_1!E7<140),"",HYPERLINK("#Р2_НИОКТР_2!A6","переход на форму")) | K11: Соответствует | L11: Получены предварительные результаты исследования состояния слуха групп работников «шумовых» производств.
A12: 3 | B12: Прочее | C12: Иное | D12: =IF(OR(B12=O12,C12=O12),"",HYPERLINK("#Р3!A6","переход на форму")) -> переход на форму | E12: =IF(OR(B12=O12,C12=O12),"",IF(C12="Лекарственный препарат",HYPERLINK("#Р3_УГТ_ЛП!A6","переход на форму"),IF(C12="Медицинское изделие",HYPERLINK("#Р3_УГТ_МИ!A6","переход на форму"),IF(C12="Клинические рекомендации",HYPERLINK("#Р3_УГТ_КР!A6","переход на форму"),IF(C12="Иное",HYPERLINK("#Р3_УГТ_Иное!A6","переход на форму"),""))))) -> переход на форму | F12: =IF(OR(B12=O12,C12=O12),"",IF(C12="Лекарственный препарат",HYPERLINK("#Р3_ДОК_ЛП!A6","переход на форму"),IF(C12="Медицинское изделие",HYPERLINK("#Р3_ДОК_МИ!A6","переход на форму"),IF(C12="Клинические рекомендации",HYPERLINK("#Р3_ДОК_КР!A6","переход на форму"),IF(C12="Иное",HYPERLINK("#Р3_ДОК_Иное!A6","переход на форму"),""))))) -> переход на форму | G12: =IF(OR(B12=O12,C12=O12),"",HYPERLINK("#Р3_КТ!A6","переход на форму")) -> переход на форму | H12: =IF(OR(B12=O12,C12=O12),"",HYPERLINK("#Р3_СТ!A6","переход на форму")) -> переход на форму | I12: =IF(OR(B12=O12,C12=O12,C7<>2024),"",HYPERLINK("#Р3_НИОКТР_1!A6","переход на форму")) | J12: =IF(OR(B12=O12,C12=O12,C7<>2024,Р3_НИОКТР_1!E7<140),"",HYPERLINK("#Р3_НИОКТР_2!A6","переход на форму")) | K12: Соответствует | L12: На основании обзора литературных источников показано, что потеря слуха может быть неспецифическим симптомом COVID-19. По результатам работы опубликована 1 статья (журнал категории Q2,K1), практическое руководство, тезисы конференции).

Sheet Р1
A1: Вернуться на главную страницу
A2: Оценка вкалада результата НИР в решение приоритетных проблем медицины и здравоохранения
A3: Вид результата: | C3: =Форма!B10 -> Метод профилактики
A4: Тип результата: | C4: =Форма!C10 -> Клинические рекомендации
A5: № | B5: Укажите приоритетную проблему медицины и здравоохранения, на решение которой направлен результат НИР | C5: Оцените вклад результата НИР в ее решение в виде единственного выбора из числа приведенных вариантов.
C6: Клинический эффект | D6: Возможность импортозамещения
A7: 1 | B7: Растущая смертность от болезней системы кровообращения | X7: =SUM(C50:D50) -> 2 | Z7: =COUNTA(C7:C49) -> 1 | AA7: =COUNTA(D7:D49) -> 1
A8: 2 | B8: Повышение рисков нарушений ритма сердца: фибрилляция предсердий, желудочковые нарушения ритма сердца, внезапная сердечная смерть (ВСС), брадиаритмии
A9: 3 | B9: Артериальная гипертензия: разработка и производство отечественных антигипертензивных препаратов, отвечающих стратегии полипилл, для увеличения приверженности пациентов к терапии
A10: 4 | B10: Инфаркт миокарда: разработка и производство отечественных препаратов для тромболитической терапии
A11: 5 | B11: Инфаркт миокарда: разработка и производство отечественных медицинских изделий, применяемых для хирургических вмешательств, которые отсутствуют в Российской Федерации либо нуждаются в совершенствовании, импортозамещении
A12: 6 | B12: Острый перикардит: необходимость проведения клинических исследований для расширения показаний к применению препарата «Колхицин»
A13: 7 | B13: Острый перикардит: разработка и производство новой активной фармацевтической субстанции для производства отечественного препарата
A14: 8 | B14: Фибрилляция предсердий: разработка и производство отечественных медицинских изделий, которые отсутствуют в Российской Федерации либо нуждаются в совершенствовании, импортозамещении
A15: 9 | B15: Высокие риски передачи вируса гепатита С от матери к ребенку
A16: 10 | B16: Бронхиальная астма: проведение исследований, направленных на изучение роли маркера периостина в диагностике бронхиальной астмы
A17: 11 | B17: Бронхиальная астма: разработка и производство отечественных медицинских изделий, применяемых для диагностики, мониторинга и выбора тактики лечения при бронхиальной астме, которые отсутствуют в Российской Федерации либо нуждаются в совершенствовании, импортозамещении
A18: 12 | B18: Бронхиальная астма: разработка новых активных фармацевтических субстанций и производство отечественных лекарственных препаратов на их основе для терапии бронхиальной астмы, рекомендованных к применению в соответствии с клиническими рекомендациями
A19: 13 | B19: Сложность бесперебойного лекарственного обеспечения и диагностики пациентов с аутоиммунным лимфопролиферативным синдромом (АЛПС)
... A24: 18 | B24: Сахарный диабет: разработка и внедрение отечественных систем неинвазивного мониторинга уровня глюкозы в крови
A25: 19 | B25: Недостаточно ранее выявление злокачественных новообразований минимально инвазивным способом на амбулаторном этапе | C25: Проведен анализ частоты выявления, сроков формирования и степени выраженности снижения слуховой функции в группах сравнения по данным субъективных и объективных методов исследования слуховой функции. | D25: Нет
A26: 20 | B26: Онкология: разработка и производство отечественных иммуноонкологических и таргетных противоопухолевых препаратов
A27: 21 | B27: Онкология: разработка и производство отечественных медицинских изделий для радиотерапии, которые отсутствуют в Российской Федерации либо нуждаются в совершенствовании, импортозамещении
A28: 22 | B28: Увеличение количества ожидающих пациентов, нуждающихся в трансплантации органов
A29: 23 | B29: Ограниченное количество трансплантаций органов в год
A30: 24 | B30: Низкий уровень качества трансплантологической помощи
A31: 25 | B31: Нейрохирургия: разработка и производство отечественных медицинских изделий, которые отсутствуют в Российской Федерации либо нуждаются в совершенствовании, импортозамещении
A32: 26 | B32: Рассеянный склероз: разработка и производство отечественных лекарственных препаратов, изменяющих течение заболевания
A33: 27 | B33: Нейрохирургия: разработка базы данных исследований в вертебрологии
A34: 28 | B34: Недостаточные оперативность и качество ранней диагностики, профилактики и лечения дегенеративно-дистрофических заболеваний, в т.ч. с применением сустав-сохраняющих хирургических технологий
A35: 29 | B35: Травматология и ортопедия: разработка и производство отечественных медицинских изделий для терапии болезней органов опорно-двигательной системы, которые отсутствуют в Российской Федерации либо нуждаются в совершенствовании, импортозамещении
A36: 30 | B36: Рост распространенности функциональных зрительных расстройств у детей и взрослых
A37: 31 | B37: Офтальмология: разработка и производство отечественных медицинских изделий, которые отсутствуют в Российской Федерации либо нуждаются в совершенствовании, импортозамещении
... A49: 43 | B49: Младенческие (инфантильные) гемангиомы: разработка и производство отечественных препаратов в виде лекарственной формы «раствор для приема внутрь».
C50: =COUNTA(C7:C49) -> 1 | D50: =COUNTA(D7:D49) -> 1

Sheet Р2
A1: Вернуться на главную страницу
A2: Оценка вкалада результата НИР в решение приоритетных проблем медицины и здравоохранения
A3: Вид результата: | C3: =Форма!B11 -> Метод диагностики
A4: Тип результата: | C4: =Форма!C11 -> Клинические рекомендации
A5: № | B5: Укажите приоритетную проблему медицины и здравоохранения, на решение которой направлен результат НИР | C5: Оцените вклад результата НИР в ее решение в виде единственного выбора из числа приведенных вариантов.
C6: Клинический эффект | D6: Возможность импортозамещения
A7: 1 | B7: Растущая смертность от болезней системы кровообращения | X7: =SUM(C50:D50) -> 2 | Z7: =COUNTA(C7:C49) -> 1 | AA7: =COUNTA(D7:D49) -> 1
A8: 2 | B8: Повышение рисков нарушений ритма сердца: фибрилляция предсердий, желудочковые нарушения ритма сердца, внезапная сердечная смерть (ВСС), брадиаритмии
A9: 3 | B9: Артериальная гипертензия: разработка и производство отечественных антигипертензивных препаратов, отвечающих стратегии полипилл, для увеличения приверженности пациентов к терапии
A10: 4 | B10: Инфаркт миокарда: разработка и производство отечественных препаратов для тромболитической терапии
A11: 5 | B11: Инфаркт миокарда: разработка и производство отечественных медицинских изделий, применяемых для хирургических вмешательств, которые отсутствуют в Российской Федерации либо нуждаются в совершенствовании, импортозамещении
A12: 6 | B12: Острый перикардит: необходимость проведения клинических исследований для расширения показаний к применению препарата «Колхицин»
A13: 7 | B13: Острый перикардит: разработка и производство новой активной фармацевтической субстанции для производства отечественного препарата
A14: 8 | B14: Фибрилляция предсердий: разработка и производство отечественных медицинских изделий, которые отсутствуют в Российской Федерации либо нуждаются в совершенствовании, импортозамещении
A15: 9 | B15: Высокие риски передачи вируса гепатита С от матери к ребенку
A16: 10 | B16: Бронхиальная астма: проведение исследований, направленных на изучение роли маркера периостина в диагностике бронхиальной астмы
A17: 11 | B17: Бронхиальная астма: разработка и производство отечественных медицинских изделий, применяемых для диагностики, мониторинга и выбора тактики лечения при бронхиальной астме, которые отсутствуют в Российской Федерации либо нуждаются в совершенствовании, импортозамещении
A18: 12 | B18: Бронхиальная астма: разработка новых активных фармацевтических субстанций и производство отечественных лекарственных препаратов на их основе для терапии бронхиальной астмы, рекомендованных к применению в соответствии с клиническими рекомендациями
A19: 13 | B19: Сложность бесперебойного лекарственного обеспечения и диагностики пациентов с аутоиммунным лимфопролиферативным синдромом (АЛПС)
... A24: 18 | B24: Сахарный диабет: разработка и внедрение отечественных систем неинвазивного мониторинга уровня глюкозы в крови
A25: 19 | B25: Недостаточно ранее выявление злокачественных новообразований минимально инвазивным способом на амбулаторном этапе | C25: У лиц, перенесших COVID-19, выявлено не только подавление спектра вызванной отоакустической эмиссии, но и снижение амплитуды ответа на звуковую стимуляцию. | D25: Нет
A26: 20 | B26: Онкология: разработка и производство отечественных иммуноонкологических и таргетных противоопухолевых препаратов
A27: 21 | B27: Онкология: разработка и производство отечественных медицинских изделий для радиотерапии, которые отсутствуют в Российской Федерации либо нуждаются в совершенствовании, импортозамещении
A28: 22 | B28: Увеличение количества ожидающих пациентов, нуждающихся в трансплантации органов
A29: 23 | B29: Ограниченное количество трансплантаций органов в год
A30: 24 | B30: Низкий уровень качества трансплантологической помощи
A31: 25 | B31: Нейрохирургия: разработка и производство отечественных медицинских изделий, которые отсутствуют в Российской Федерации либо нуждаются в совершенствовании, импортозамещении
A32: 26 | B32: Рассеянный склероз: разработка и производство отечественных лекарственных препаратов, изменяющих течение заболевания
A33: 27 | B33: Нейрохирургия: разработка базы данных исследований в вертебрологии
A34: 28 | B34: Недостаточные оперативность и качество ранней диагностики, профилактики и лечения дегенеративно-дистрофических заболеваний, в т.ч. с применением сустав-сохраняющих хирургических технологий
A35: 29 | B35: Травматология и ортопедия: разработка и производство отечественных медицинских изделий для терапии болезней органов опорно-двигательной системы, которые отсутствуют в Российской Федерации либо нуждаются в совершенствовании, импортозамещении
A36: 30 | B36: Рост распространенности функциональных зрительных расстройств у детей и взрослых
A37: 31 | B37: Офтальмология: разработка и производство отечественных медицинских изделий, которые отсутствуют в Российской Федерации либо нуждаются в совершенствовании, импортозамещении
... A49: 43 | B49: Младенческие (инфантильные) гемангиомы: разработка и производство отечественных препаратов в виде лекарственной формы «раствор для приема внутрь».
C50: =COUNTA(C7:C49) -> 1 | D50: =COUNTA(D7:D49) -> 1

Sheet Р3
A1: Вернуться на главную страницу
A2: Оценка вкалада результата НИР в решение приоритетных проблем медицины и здравоохранения
A3: Вид результата: | C3: =Форма!B12 -> Прочее
A4: Тип результата: | C4: =Форма!C12 -> Иное
A5: № | B5: Укажите приоритетную проблему медицины и здравоохранения, на решение которой направлен результат НИР | C5: Оцените вклад результата НИР в ее решение в виде единственного выбора из числа приведенных вариантов.
C6: Клинический эффект | D6: Возможность импортозамещения
A7: 1 | B7: Растущая смертность от болезней системы кровообращения | X7: =SUM(C50:D50) -> 2 | Z7: =COUNTA(C7:C49) -> 1 | AA7: =COUNTA(D7:D49) -> 1
A8: 2 | B8: Повышение рисков нарушений ритма сердца: фибрилляция предсердий, желудочковые нарушения ритма сердца, внезапная сердечная смерть (ВСС), брадиаритмии
A9: 3 | B9: Артериальная гипертензия: разработка и производство отечественных антигипертензивных препаратов, отвечающих стратегии полипилл, для увеличения приверженности пациентов к терапии
A10: 4 | B10: Инфаркт миокарда: разработка и производство отечественных препаратов для тромболитической терапии
A11: 5 | B11: Инфаркт миокарда: разработка и производство отечественных медицинских изделий, применяемых для хирургических вмешательств, которые отсутствуют в Российской Федерации либо нуждаются в совершенствовании, импортозамещении
A12: 6 | B12: Острый перикардит: необходимость проведения клинических исследований для расширения показаний к применению препарата «Колхицин»
A13: 7 | B13: Острый перикардит: разработка и производство новой активной фармацевтической субстанции для производства отечественного препарата
A14: 8 | B14: Фибрилляция предсердий: разработка и производство отечественных медицинских изделий, которые отсутствуют в Российской Федерации либо нуждаются в совершенствовании, импортозамещении
A15: 9 | B15: Высокие риски передачи вируса гепатита С от матери к ребенку
A16: 10 | B16: Бронхиальная астма: проведение исследований, направленных на изучение роли маркера периостина в диагностике бронхиальной астмы
A17: 11 | B17: Бронхиальная астма: разработка и производство отечественных медицинских изделий, применяемых для диагностики, мониторинга и выбора тактики лечения при бронхиальной астме, которые отсутствуют в Российской Федерации либо нуждаются в совершенствовании, импортозамещении
A18: 12 | B18: Бронхиальная астма: разработка новых активных фармацевтических субстанций и производство отечественных лекарственных препаратов на их основе для терапии бронхиальной астмы, рекомендованных к применению в соответствии с клиническими рекомендациями
A19: 13 | B19: Сложность бесперебойного лекарственного обеспечения и диагностики пациентов с аутоиммунным лимфопролиферативным синдромом (АЛПС)
... A24: 18 | B24: Сахарный диабет: разработка и внедрение отечественных систем неинвазивного мониторинга уровня глюкозы в крови
A25: 19 | B25: Недостаточно ранее выявление злокачественных новообразований минимально инвазивным способом на амбулаторном этапе | C25: Проведен анализ литературных данных о влиянии коронавирусной инфекции COVID-19 на состояние слуховой функции. Выявлено, что потеря слуха может быть неспецифическим симптомом COVID-19. | D25: Нет
A26: 20 | B26: Онкология: разработка и производство отечественных иммуноонкологических и таргетных противоопухолевых препаратов
A27: 21 | B27: Онкология: разработка и производство отечественных медицинских изделий для радиотерапии, которые отсутствуют в Российской Федерации либо нуждаются в совершенствовании, импортозамещении
A28: 22 | B28: Увеличение количества ожидающих пациентов, нуждающихся в трансплантации органов
A29: 23 | B29: Ограниченное количество трансплантаций органов в год
A30: 24 | B30: Низкий уровень качества трансплантологической помощи
A31: 25 | B31: Нейрохирургия: разработка и производство отечественных медицинских изделий, которые отсутствуют в Российской Федерации либо нуждаются в совершенствовании, импортозамещении
A32: 26 | B32: Рассеянный склероз: разработка и производство отечественных лекарственных препаратов, изменяющих течение заболевания
A33: 27 | B33: Нейрохирургия: разработка базы данных исследований в вертебрологии
A34: 28 | B34: Недостаточные оперативность и качество ранней диагностики, профилактики и лечения дегенеративно-дистрофических заболеваний, в т.ч. с применением сустав-сохраняющих хирургических технологий
A35: 29 | B35: Травматология и ортопедия: разработка и производство отечественных медицинских изделий для терапии болезней органов опорно-двигательной системы, которые отсутствуют в Российской Федерации либо нуждаются в совершенствовании, импортозамещении
A36: 30 | B36: Рост распространенности функциональных зрительных расстройств у детей и взрослых
A37: 31 | B37: Офтальмология: разработка и производство отечественных медицинских изделий, которые отсутствуют в Российской Федерации либо нуждаются в совершенствовании, импортозамещении
... A49: 43 | B49: Младенческие (инфантильные) гемангиомы: разработка и производство отечественных препаратов в виде лекарственной формы «раствор для приема внутрь».
C50: =COUNTA(C7:C49) -> 1 | D50: =COUNTA(D7:D49) -> 1

Sheet Клинический эффект
A1: Клинический эффект для оценки вкалада результата НИР в решение приоритетных проблем медицины и здравоохранения
A2: № | B2: Наименование
A4: 1 | B4: Снижение смертности
A5: 2 | B5: Снижение инвалидизации в несовершеннолетнем возрасте (предотвращение инвалидности, достижение отсрочки в наступлении инвалидности, снятие инвалидности)
A6: 3 | B6: Снижение инвалидизации в совершеннолетнем возрасте (предотвращение инвалидности, достижение отсрочки в наступлении инвалидности, переход в менее тяжелую группу инвалидности, снятие инвалидности)
A7: 4 | B7: Снижение временной утраты трудоспособности (более 14 дней)
A8: 5 | B8: Снижение временной утраты трудоспособности (до 14 дней)
A9: 6 | B9: Повышение качества жизни, связанного с состоянием здоровья

Sheet Возможность импортозамещения
A1: Возможность импортозамещения
A2: № | B2: Возможность
A4: 1 | B4: Имеется возможность серийного производства в России
A5: 2 | B5: Отсутствует возможность серийного производства в России

Sheet Р1_УГТ_ЛП
A1: Вернуться на главную страницу
A2: Перечень задач
A3: Вид результата: | C3: =Форма!B10 -> Метод профилактики
A4: Тип результата: | C4: =Форма!C10 -> Клинические рекомендации
A6: Отметьте все задачи, полностью решенные к моменту завершения НИР или данного этапа НИР в рамках достижения УГТ оцениваемого научного результата
A7: Проведен аналитический обзор научной, медицинской, технической литературы по теме | D7: FALSE | E7: =IF(LEN(D7)>4,1,0) -> 0
A8: Выявлены механизмы возникновения заболевания, определены молекулярные мишени | D8: FALSE | E8: =IF(LEN(D8)>4,1,0) -> 0
A9: Проведено изучение библиотек данных с целью выбора потенциального кандидата прототипа молекулы | D9: FALSE | E9: =IF(LEN(D9)>4,1,0) -> 0
A10: Разработан дизайн исследования | D10: FALSE | E10: =IF(LEN(D10)>4,1,0) -> 0
A11: Подтверждены научные принципы нового ЛС | D11: FALSE | E11: =IF(LEN(D11)>4,1,0) -> 0
A12: Докинг/скрининг/программное прогнозирование с целью выбора кандидата | D12: FALSE | E12: =IF(LEN(D12)>4,1,0) -> 0
A13: Предварительно определены целевые показатели качества | D13: FALSE | E13: =IF(LEN(D13)>4,1,0) -> 0
A14: Определено целевое назначение нового ЛС | D14: FALSE | E14: =IF(LEN(D14)>4,1,0) -> 0
A15: Подтверждена востребованность нового ЛС | D15: FALSE | E15: =IF(LEN(D15)>4,1,0) -> 0
A16: Сформулирована общая концепция нового ЛС | D16: FALSE | E16: =IF(LEN(D16)>4,1,0) -> 0
A17: Сформулирована ожидаемая выгода для заказчика нового ЛС с учетом существующих на рынке аналогов | D17: FALSE | E17: =IF(LEN(D17)>4,1,0) -> 0
A18: Сформулирована ожидаемая выгода для возможных потребителей нового ЛС с учетом существующих на рынке аналогов | D18: FALSE | E18: =IF(LEN(D18)>4,1,0) -> 0
... A61: Подготовлены отчеты КИ II фазы | D61: FALSE | E61: =IF(LEN(D61)>4,1,0) -> 0
E62: =SUM(E7:E61) -> 0

Sheet Р2_УГТ_ЛП
A1: Вернуться на главную страницу
A2: Перечень задач
A3: Вид результата: | C3: =Форма!B11 -> Метод диагностики
A4: Тип результата: | C4: =Форма!C11 -> Клинические рекомендации
A6: Отметьте все задачи, полностью решенные к моменту завершения НИР или данного этапа НИР в рамках достижения УГТ оцениваемого научного результата
A7: Проведен аналитический обзор научной, медицинской, технической литературы по теме | D7: FALSE | E7: =IF(LEN(D7)>4,1,0) -> 0
A8: Выявлены механизмы возникновения заболевания, определены молекулярные мишени | D8: FALSE | E8: =IF(LEN(D8)>4,1,0) -> 0
A9: Проведено изучение библиотек данных с целью выбора потенциального кандидата прототипа молекулы | D9: FALSE | E9: =IF(LEN(D9)>4,1,0) -> 0
A10: Разработан дизайн исследования | D10: FALSE | E10: =IF(LEN(D10)>4,1,0) -> 0
A11: Подтверждены научные принципы нового ЛС | D11: FALSE | E11: =IF(LEN(D11)>4,1,0) -> 0
A12: Докинг/скрининг/программное прогнозирование с целью выбора кандидата | D12: FALSE | E12: =IF(LEN(D12)>4,1,0) -> 0
A13: Предварительно определены целевые показатели качества | D13: FALSE | E13: =IF(LEN(D13)>4,1,0) -> 0
A14: Определено целевое назначение нового ЛС | D14: FALSE | E14: =IF(LEN(D14)>4,1,0) -> 0
A15: Подтверждена востребованность нового ЛС | D15: FALSE | E15: =IF(LEN(D15)>4,1,0) -> 0
A16: Сформулирована общая концепция нового ЛС | D16: FALSE | E16: =IF(LEN(D16)>4,1,0) -> 0
A17: Сформулирована ожидаемая выгода для заказчика нового ЛС с учетом существующих на рынке аналогов | D17: FALSE | E17: =IF(LEN(D17)>4,1,0) -> 0
A18: Сформулирована ожидаемая выгода для возможных потребителей нового ЛС с учетом существующих на рынке аналогов | D18: FALSE | E18: =IF(LEN(D18)>4,1,0) -> 0
... A61: Подготовлены отчеты КИ II фазы | D61: FALSE | E61: =IF(LEN(D61)>4,1,0) -> 0
E62: =SUM(E7:E61) -> 0

Sheet Р3_УГТ_ЛП
A1: Вернуться на главную страницу
A2: Перечень задач
A3: Вид результата: | C3: =Форма!B12 -> Прочее
A4: Тип результата: | C4: =Форма!C12 -> Иное
A6: Отметьте все задачи, полностью решенные к моменту завершения НИР или данного этапа НИР в рамках достижения УГТ оцениваемого научного результата
A7: Проведен аналитический обзор научной, медицинской, технической литературы по теме | D7: FALSE | E7: =IF(LEN(D7)>4,1,0) -> 0
A8: Выявлены механизмы возникновения заболевания, определены молекулярные мишени | D8: FALSE | E8: =IF(LEN(D8)>4,1,0) -> 0
A9: Проведено изучение библиотек данных с целью выбора потенциального кандидата прототипа молекулы | D9: FALSE | E9: =IF(LEN(D9)>4,1,0) -> 0
A10: Разработан дизайн исследования | D10: FALSE | E10: =IF(LEN(D10)>4,1,0) -> 0
A11: Подтверждены научные принципы нового ЛС | D11: FALSE | E11: =IF(LEN(D11)>4,1,0) -> 0
A12: Докинг/скрининг/программное прогнозирование с целью выбора кандидата | D12: FALSE | E12: =IF(LEN(D12)>4,1,0) -> 0
A13: Предварительно определены целевые показатели качества | D13: FALSE | E13: =IF(LEN(D13)>4,1,0) -> 0
A14: Определено целевое назначение нового ЛС | D14: FALSE | E14: =IF(LEN(D14)>4,1,0) -> 0
A15: Подтверждена востребованность нового ЛС | D15: FALSE | E15: =IF(LEN(D15)>4,1,0) -> 0
A16: Сформулирована общая концепция нового ЛС | D16: FALSE | E16: =IF(LEN(D16)>4,1,0) -> 0
A17: Сформулирована ожидаемая выгода для заказчика нового ЛС с учетом существующих на рынке аналогов | D17: FALSE | E17: =IF(LEN(D17)>4,1,0) -> 0
A18: Сформулирована ожидаемая выгода для возможных потребителей нового ЛС с учетом существующих на рынке аналогов | D18: FALSE | E18: =IF(LEN(D18)>4,1,0) -> 0
... A61: Подготовлены отчеты КИ II фазы | D61: FALSE | E61: =IF(LEN(D61)>4,1,0) -> 0
E62: =SUM(E7:E61) -> 0

Sheet Р1_УГТ_МИ
A1: Вернуться на главную страницу
A2: Перечень задач
A3: Вид результата: | C3: =Форма!B10 -> Метод профилактики
A4: Тип результата: | C4: =Форма!C10 -> Клинические рекомендации
A6: Отметьте все задачи, полностью решенные к моменту завершения НИР или данного этапа НИР в рамках достижения УГТ оцениваемого научного результата
A7: Проведен обзор технической литературы по теме | D7: FALSE | E7: =IF(LEN(D7)>4,1,0) -> 0
A8: Проведен обзор маркетинговой литературы по теме | D8: FALSE | E8: =IF(LEN(D8)>4,1,0) -> 0
A9: Подтверждены научные принципы нового продукта/технологии | D9: FALSE | E9: =IF(LEN(D9)>4,1,0) -> 0
A10: Подтверждена востребованность нового продукта/технологии | D10: FALSE | E10: =IF(LEN(D10)>4,1,0) -> 0
A11: Сформулирована общая концепция нового продукта/технологии | D11: FALSE | E11: =IF(LEN(D11)>4,1,0) -> 0
A12: Сформулирована ожидаемая выгода для заказчика нового продукта и (или) технологии с учетом существующих на рынке продуктов и (или) технологий | D12: FALSE | E12: =IF(LEN(D12)>4,1,0) -> 0
A13: Сформулирована ожидаемая выгода для возможных потребителей нового продукта и (или) технологии с учетом существующих на рынке продуктов и (или) технологий | D13: FALSE | E13: =IF(LEN(D13)>4,1,0) -> 0
A14: Сформулирована технологическая концепция нового продукта и (или) технологии | D14: FALSE | E14: =IF(LEN(D14)>4,1,0) -> 0
A15: Проведены патентные исследования | D15: FALSE | E15: =IF(LEN(D15)>4,1,0) -> 0
A16: Выполнена проверка концепции экспериментальными методами для доказательства эффективности использования идеи | D16: FALSE | E16: =IF(LEN(D16)>4,1,0) -> 0
A17: Выбраны и описаны критические элементы технологии, необходимые для конечного применения | D17: FALSE | E17: =IF(LEN(D17)>4,1,0) -> 0
A18: Сформулировано предварительное техническое задание на макет | D18: FALSE | E18: =IF(LEN(D18)>4,1,0) -> 0
... A60: Техническая спецификация системы готова и достаточна для детального проектирования конечной технологии - для разработки конструкторской документации, с литерой "О2" | D60: FALSE | E60: =IF(LEN(D60)>4,1,0) -> 0
E61: =SUM(E7:E60) -> 0

Sheet Р2_УГТ_МИ
A1: Вернуться на главную страницу
A2: Перечень задач
A3: Вид результата: | C3: =Форма!B11 -> Метод диагностики
A4: Тип результата: | C4: =Форма!C11 -> Клинические рекомендации
A6: Отметьте все задачи, полностью решенные к моменту завершения НИР или данного этапа НИР в рамках достижения УГТ оцениваемого научного результата
A7: Проведен обзор технической литературы по теме | D7: FALSE | E7: =IF(LEN(D7)>4,1,0) -> 0
A8: Проведен обзор маркетинговой литературы по теме | D8: FALSE | E8: =IF(LEN(D8)>4,1,0) -> 0
A9: Подтверждены научные принципы нового продукта/технологии | D9: FALSE | E9: =IF(LEN(D9)>4,1,0) -> 0
A10: Подтверждена востребованность нового продукта/технологии | D10: FALSE | E10: =IF(LEN(D10)>4,1,0) -> 0
A11: Сформулирована общая концепция нового продукта/технологии | D11: FALSE | E11: =IF(LEN(D11)>4,1,0) -> 0
A12: Сформулирована ожидаемая выгода для заказчика нового продукта и (или) технологии с учетом существующих на рынке продуктов и (или) технологий | D12: FALSE | E12: =IF(LEN(D12)>4,1,0) -> 0
A13: Сформулирована ожидаемая выгода для возможных потребителей нового продукта и (или) технологии с учетом существующих на рынке продуктов и (или) технологий | D13: FALSE | E13: =IF(LEN(D13)>4,1,0) -> 0
A14: Сформулирована технологическая концепция нового продукта и (или) технологии | D14: FALSE | E14: =IF(LEN(D14)>4,1,0) -> 0
A15: Проведены патентные исследования | D15: FALSE | E15: =IF(LEN(D15)>4,1,0) -> 0
A16: Выполнена проверка концепции экспериментальными методами для доказательства эффективности использования идеи | D16: FALSE | E16: =IF(LEN(D16)>4,1,0) -> 0
A17: Выбраны и описаны критические элементы технологии, необходимые для конечного применения | D17: FALSE | E17: =IF(LEN(D17)>4,1,0) -> 0
A18: Сформулировано предварительное техническое задание на макет | D18: FALSE | E18: =IF(LEN(D18)>4,1,0) -> 0
... A60: Техническая спецификация системы готова и достаточна для детального проектирования конечной технологии - для разработки конструкторской документации, с литерой "О2" | D60: FALSE | E60: =IF(LEN(D60)>4,1,0) -> 0
E61: =SUM(E7:E60) -> 0

Sheet Р3_УГТ_МИ
A1: Вернуться на главную страницу
A2: Перечень задач
A3: Вид результата: | C3: =Форма!B12 -> Прочее
A4: Тип результата: | C4: =Форма!C12 -> Иное
A6: Отметьте все задачи, полностью решенные к моменту завершения НИР или данного этапа НИР в рамках достижения УГТ оцениваемого научного результата
A7: Проведен обзор технической литературы по теме | D7: FALSE | E7: =IF(LEN(D7)>4,1,0) -> 0
A8: Проведен обзор маркетинговой литературы по теме | D8: FALSE | E8: =IF(LEN(D8)>4,1,0) -> 0
A9: Подтверждены научные принципы нового продукта/технологии | D9: FALSE | E9: =IF(LEN(D9)>4,1,0) -> 0
A10: Подтверждена востребованность нового продукта/технологии | D10: FALSE | E10: =IF(LEN(D10)>4,1,0) -> 0
A11: Сформулирована общая концепция нового продукта/технологии | D11: FALSE | E11: =IF(LEN(D11)>4,1,0) -> 0
A12: Сформулирована ожидаемая выгода для заказчика нового продукта и (или) технологии с учетом существующих на рынке продуктов и (или) технологий | D12: FALSE | E12: =IF(LEN(D12)>4,1,0) -> 0
A13: Сформулирована ожидаемая выгода для возможных потребителей нового продукта и (или) технологии с учетом существующих на рынке продуктов и (или) технологий | D13: FALSE | E13: =IF(LEN(D13)>4,1,0) -> 0
A14: Сформулирована технологическая концепция нового продукта и (или) технологии | D14: FALSE | E14: =IF(LEN(D14)>4,1,0) -> 0
A15: Проведены патентные исследования | D15: FALSE | E15: =IF(LEN(D15)>4,1,0) -> 0
A16: Выполнена проверка концепции экспериментальными методами для доказательства эффективности использования идеи | D16: FALSE | E16: =IF(LEN(D16)>4,1,0) -> 0
A17: Выбраны и описаны критические элементы технологии, необходимые для конечного применения | D17: FALSE | E17: =IF(LEN(D17)>4,1,0) -> 0
A18: Сформулировано предварительное техническое задание на макет | D18: FALSE | E18: =IF(LEN(D18)>4,1,0) -> 0
... A60: Техническая спецификация системы готова и достаточна для детального проектирования конечной технологии - для разработки конструкторской документации, с литерой "О2" | D60: FALSE | E60: =IF(LEN(D60)>4,1,0) -> 0
E61: =SUM(E7:E60) -> 0

Sheet Р1_УГТ_КР
A1: Вернуться на главную страницу
A2: Перечень задач
A3: Вид результата: | C3: =Форма!B10 -> Метод профилактики
A4: Тип результата: | C4: =Форма!C10 -> Клинические рекомендации
A6: Отметьте все задачи, полностью решенные к моменту завершения НИР или данного этапа НИР в рамках достижения УГТ оцениваемого научного результата
A7: Проведен аналитический обзор научной, медицинской, технической литературы | D7: TRUE | E7: =IF(LEN(D7)>4,1,0) -> 1
A8: Собрана и описана информация по заболеванию или состоянию (группы заболеваний или состояний): этиология и патогенез, эпидемиология, классификация, клиническая картина | D8: TRUE | E8: =IF(LEN(D8)>4,1,0) -> 1
A9: Подтверждены научные принципы нового продукта | D9: TRUE | E9: =IF(LEN(D9)>4,1,0) -> 1
A10: Предварительно определены целевые показатели качества | D10: TRUE | E10: =IF(LEN(D10)>4,1,0) -> 1
A11: Определено целевое назначение продукта | D11: TRUE | E11: =IF(LEN(D11)>4,1,0) -> 1
A12: Подтверждена востребованность нового продукта | D12: TRUE | E12: =IF(LEN(D12)>4,1,0) -> 1
A13: Сформулирована общая концепция нового продукта | D13: TRUE | E13: =IF(LEN(D13)>4,1,0) -> 1
A14: Сформулирована ожидаемая выгода для заказчика | D14: TRUE | E14: =IF(LEN(D14)>4,1,0) -> 1
A15: Сформулирована ожидаемая выгода для потребителей | D15: TRUE | E15: =IF(LEN(D15)>4,1,0) -> 1
A16: Проведены патентные исследования | D16: FALSE | E16: =IF(LEN(D16)>4,1,0) -> 0
A17: Выполнена проверка концепции экспериментальными методами для доказательства эффективности использования идеи | D17: FALSE | E17: =IF(LEN(D17)>4,1,0) -> 0
A18: Проведены экспериментальные работы, подтверждающие применимость разрабатываемых методов диагностики/лечения/реабилитации/профилактики для включения в клинические рекомендации | D18: TRUE | E18: =IF(LEN(D18)>4,1,0) -> 1
... A39: Проект клинических рекомендаций доработан | D39: FALSE | E39: =IF(LEN(D39)>4,1,0) -> 0
E40: =SUM(E7:E39) -> 14

Sheet Р2_УГТ_КР
A1: Вернуться на главную страницу
A2: Перечень задач
A3: Вид результата: | C3: =Форма!B11 -> Метод диагностики
A4: Тип результата: | C4: =Форма!C11 -> Клинические рекомендации
A6: Отметьте все задачи, полностью решенные к моменту завершения НИР или данного этапа НИР в рамках достижения УГТ оцениваемого научного результата
A7: Проведен аналитический обзор научной, медицинской, технической литературы | D7: TRUE | E7: =IF(LEN(D7)>4,1,0) -> 1
A8: Собрана и описана информация по заболеванию или состоянию (группы заболеваний или состояний): этиология и патогенез, эпидемиология, классификация, клиническая картина | D8: TRUE | E8: =IF(LEN(D8)>4,1,0) -> 1
A9: Подтверждены научные принципы нового продукта | D9: TRUE | E9: =IF(LEN(D9)>4,1,0) -> 1
A10: Предварительно определены целевые показатели качества | D10: TRUE | E10: =IF(LEN(D10)>4,1,0) -> 1
A11: Определено целевое назначение продукта | D11: TRUE | E11: =IF(LEN(D11)>4,1,0) -> 1
A12: Подтверждена востребованность нового продукта | D12: TRUE | E12: =IF(LEN(D12)>4,1,0) -> 1
A13: Сформулирована общая концепция нового продукта | D13: TRUE | E13: =IF(LEN(D13)>4,1,0) -> 1
A14: Сформулирована ожидаемая выгода для заказчика | D14: TRUE | E14: =IF(LEN(D14)>4,1,0) -> 1
A15: Сформулирована ожидаемая выгода для потребителей | D15: TRUE | E15: =IF(LEN(D15)>4,1,0) -> 1
A16: Проведены патентные исследования | D16: FALSE | E16: =IF(LEN(D16)>4,1,0) -> 0
A17: Выполнена проверка концепции экспериментальными методами для доказательства эффективности использования идеи | D17: TRUE | E17: =IF(LEN(D17)>4,1,0) -> 1
A18: Проведены экспериментальные работы, подтверждающие применимость разрабатываемых методов диагностики/лечения/реабилитации/профилактики для включения в клинические рекомендации | D18: TRUE | E18: =IF(LEN(D18)>4,1,0) -> 1
... A39: Проект клинических рекомендаций доработан | D39: FALSE | E39: =IF(LEN(D39)>4,1,0) -> 0
E40: =SUM(E7:E39) -> 13

Sheet Р3_УГТ_КР
A1: Вернуться на главную страницу
A2: Перечень задач
A3: Вид результата: | C3: =Форма!B12 -> Прочее
A4: Тип результата: | C4: =Форма!C12 -> Иное
A6: Отметьте все задачи, полностью решенные к моменту завершения НИР или данного этапа НИР в рамках достижения УГТ оцениваемого научного результата
A7: Проведен аналитический обзор научной, медицинской, технической литературы | D7: FALSE | E7: =IF(LEN(D7)>4,1,0) -> 0
A8: Собрана и описана информация по заболеванию или состоянию (группы заболеваний или состояний): этиология и патогенез, эпидемиология, классификация, клиническая картина | D8: FALSE | E8: =IF(LEN(D8)>4,1,0) -> 0
A9: Подтверждены научные принципы нового продукта | D9: FALSE | E9: =IF(LEN(D9)>4,1,0) -> 0
A10: Предварительно определены целевые показатели качества | D10: FALSE | E10: =IF(LEN(D10)>4,1,0) -> 0
A11: Определено целевое назначение продукта | D11: FALSE | E11: =IF(LEN(D11)>4,1,0) -> 0
A12: Подтверждена востребованность нового продукта | D12: FALSE | E12: =IF(LEN(D12)>4,1,0) -> 0
A13: Сформулирована общая концепция нового продукта | D13: FALSE | E13: =IF(LEN(D13)>4,1,0) -> 0
A14: Сформулирована ожидаемая выгода для заказчика | D14: FALSE | E14: =IF(LEN(D14)>4,1,0) -> 0
A15: Сформулирована ожидаемая выгода для потребителей | D15: FALSE | E15: =IF(LEN(D15)>4,1,0) -> 0
A16: Проведены патентные исследования | D16: FALSE | E16: =IF(LEN(D16)>4,1,0) -> 0
A17: Выполнена проверка концепции экспериментальными методами для доказательства эффективности использования идеи | D17: FALSE | E17: =IF(LEN(D17)>4,1,0) -> 0
A18: Проведены экспериментальные работы, подтверждающие применимость разрабатываемых методов диагностики/лечения/реабилитации/профилактики для включения в клинические рекомендации | D18: FALSE | E18: =IF(LEN(D18)>4,1,0) -> 0
... A39: Проект клинических рекомендаций доработан | D39: FALSE | E39: =IF(LEN(D39)>4,1,0) -> 0
E40: =SUM(E7:E39) -> 0

Sheet Р1_УГТ_Иное
A1: Вернуться на главную страницу
A2: Перечень задач
A3: Вид результата: | C3: =Форма!B10 -> Метод профилактики
A4: Тип результата: | C4: =Форма!C10 -> Клинические рекомендации
A6: Отметьте все задачи, полностью решенные к моменту завершения НИР или данного этапа НИР в рамках достижения УГТ оцениваемого научного результата
A7: Проведен аналитический обзор технической, научной, медицинской и маркетинговой литературы по теме | D7: FALSE | E7: =IF(LEN(D7)>4,1,0) -> 0
A8: Выявлены новые закономерности, принципы, статистические явления в сфере медицины и здравоохранения | D8: FALSE | E8: =IF(LEN(D8)>4,1,0) -> 0
A9: Определена проблема медицины и здравоохранения, на решение которой направлен результат исследования/разработки | D9: FALSE | E9: =IF(LEN(D9)>4,1,0) -> 0
A10: Сформулирована идея решения проблемы и общая концепция получения результата исследования/разработки | D10: FALSE | E10: =IF(LEN(D10)>4,1,0) -> 0
A11: Подтверждены научные принципы результата исследования/разработки | D11: FALSE | E11: =IF(LEN(D11)>4,1,0) -> 0
A12: Подтверждена востребованность результата исследования/разработки | D12: FALSE | E12: =IF(LEN(D12)>4,1,0) -> 0
A13: Сформулирована ожидаемая выгода для заказчика результата исследования/разработки с учетом существующих на рынке продуктов и (или) технологий | D13: FALSE | E13: =IF(LEN(D13)>4,1,0) -> 0
A14: Сформулирована ожидаемая выгода для возможных потребителей результата исследования/разработки с учетом существующих на рынке продуктов и (или) технологий | D14: FALSE | E14: =IF(LEN(D14)>4,1,0) -> 0
E15: =SUM(E7:E14) -> 0

Sheet Р2_УГТ_Иное
A1: Вернуться на главную страницу
A2: Перечень задач
A3: Вид результата: | C3: =Форма!B11 -> Метод диагностики
A4: Тип результата: | C4: =Форма!C11 -> Клинические рекомендации
A6: Отметьте все задачи, полностью решенные к моменту завершения НИР или данного этапа НИР в рамках достижения УГТ оцениваемого научного результата
A7: Проведен аналитический обзор технической, научной, медицинской и маркетинговой литературы по теме | D7: FALSE | E7: =IF(LEN(D7)>4,1,0) -> 0
A8: Выявлены новые закономерности, принципы, статистические явления в сфере медицины и здравоохранения | D8: FALSE | E8: =IF(LEN(D8)>4,1,0) -> 0
A9: Определена проблема медицины и здравоохранения, на решение которой направлен результат исследования/разработки | D9: FALSE | E9: =IF(LEN(D9)>4,1,0) -> 0
A10: Сформулирована идея решения проблемы и общая концепция получения результата исследования/разработки | D10: FALSE | E10: =IF(LEN(D10)>4,1,0) -> 0
A11: Подтверждены научные принципы результата исследования/разработки | D11: FALSE | E11: =IF(LEN(D11)>4,1,0) -> 0
A12: Подтверждена востребованность результата исследования/разработки | D12: FALSE | E12: =IF(LEN(D12)>4,1,0) -> 0
A13: Сформулирована ожидаемая выгода для заказчика результата исследования/разработки с учетом существующих на рынке продуктов и (или) технологий | D13: FALSE | E13: =IF(LEN(D13)>4,1,0) -> 0
A14: Сформулирована ожидаемая выгода для возможных потребителей результата исследования/разработки с учетом существующих на рынке продуктов и (или) технологий | D14: FALSE | E14: =IF(LEN(D14)>4,1,0) -> 0
E15: =SUM(E7:E14) -> 0

Sheet Р3_УГТ_Иное
A1: Вернуться на главную страницу
A2: Перечень задач
A3: Вид результата: | C3: =Форма!B12 -> Прочее
A4: Тип результата: | C4: =Форма!C12 -> Иное
A6: Отметьте все задачи, полностью решенные к моменту завершения НИР или данного этапа НИР в рамках достижения УГТ оцениваемого научного результата
A7: Проведен аналитический обзор технической, научной, медицинской и маркетинговой литературы по теме | D7: TRUE | E7: =IF(LEN(D7)>4,1,0) -> 1
A8: Выявлены новые закономерности, принципы, статистические явления в сфере медицины и здравоохранения | D8: TRUE | E8: =IF(LEN(D8)>4,1,0) -> 1
A9: Определена проблема медицины и здравоохранения, на решение которой направлен результат исследования/разработки | D9: TRUE | E9: =IF(LEN(D9)>4,1,0) -> 1
A10: Сформулирована идея решения проблемы и общая концепция получения результата исследования/разработки | D10: TRUE | E10: =IF(LEN(D10)>4,1,0) -> 1
A11: Подтверждены научные принципы результата исследования/разработки | D11: TRUE | E11: =IF(LEN(D11)>4,1,0) -> 1
A12: Подтверждена востребованность результата исследования/разработки | D12: TRUE | E12: =IF(LEN(D12)>4,1,0) -> 1
A13: Сформулирована ожидаемая выгода для заказчика результата исследования/разработки с учетом существующих на рынке продуктов и (или) технологий | D13: TRUE | E13: =IF(LEN(D13)>4,1,0) -> 1
A14: Сформулирована ожидаемая выгода для возможных потребителей результата исследования/разработки с учетом существующих на рынке продуктов и (или) технологий | D14: TRUE | E14: =IF(LEN(D14)>4,1,0) -> 1
E15: =SUM(E7:E14) -> 8

Sheet Р1_ДОК_ЛП
A1: Вернуться на главную страницу
A2: Перечень информационных материалов
A3: Вид результата: | C3: =Форма!B10 -> Метод профилактики
A4: Тип результата: | C4: =Форма!C10 -> Клинические рекомендации
A6: Отметьте все информационные материалы, которые, по Вашей оценке, имеются в отчетной документации о результатах НИР
A7: Материалы о механизмах возникновения заболевания в отчете о НИР | D7: FALSE | E7: =IF(LEN(D7)>4,1,0) -> 0
A8: Материалы о молекулярных мишенях в отчете о НИР | D8: FALSE | E8: =IF(LEN(D8)>4,1,0) -> 0
A9: Материалы о проведенном докинге/программном прогнозировании для выбора кандидатных молекул в отчете о НИР | D9: FALSE | E9: =IF(LEN(D9)>4,1,0) -> 0
A10: Публикация о механизмах возникновения заболевания | D10: FALSE | E10: =IF(LEN(D10)>4,1,0) -> 0
A11: Публикация о молекулярных мишенях | D11: FALSE | E11: =IF(LEN(D11)>4,1,0) -> 0
A12: Публикация о проведенном докинге/программном прогнозировании для выбора кандидатных молекул | D12: FALSE | E12: =IF(LEN(D12)>4,1,0) -> 0
A13: Монография о механизмах возникновения заболевания/ молекулярных мишенях/ проведенном докинге/программном прогнозировании для выбора кандидатных молекул | D13: FALSE | E13: =IF(LEN(D13)>4,1,0) -> 0
A14: Экспертное заключение о возможности разработки лекарственного средства | D14: FALSE | E14: =IF(LEN(D14)>4,1,0) -> 0
A15: Пояснительная записка о возможности разработки лекарственного средства | D15: FALSE | E15: =IF(LEN(D15)>4,1,0) -> 0
A16: Презентация о механизмах возникновения заболевания/ молекулярных мишенях/ проведенном докинге/программном прогнозировании для выбора кандидатных молекул | D16: FALSE | E16: =IF(LEN(D16)>4,1,0) -> 0
A17: Отчет о патентных исследованиях | D17: FALSE | E17: =IF(LEN(D17)>4,1,0) -> 0
A18: Материалы о методах синтеза в отчете о НИР | D18: FALSE | E18: =IF(LEN(D18)>4,1,0) -> 0
... A58: Отчеты клинических исследований (КИ II фазы) | D58: FALSE | E58: =IF(LEN(D58)>4,1,0) -> 0
E59: =SUM(E7:E58) -> 0

Sheet Р2_ДОК_ЛП
A1: Вернуться на главную страницу
A2: Перечень информационных материалов
A3: Вид результата: | C3: =Форма!B11 -> Метод диагностики
A4: Тип результата: | C4: =Форма!C11 -> Клинические рекомендации
A6: Отметьте все информационные материалы, которые, по Вашей оценке, имеются в отчетной документации о результатах НИР
A7: Материалы о механизмах возникновения заболевания в отчете о НИР | D7: FALSE | E7: =IF(LEN(D7)>4,1,0) -> 0
A8: Материалы о молекулярных мишенях в отчете о НИР | D8: FALSE | E8: =IF(LEN(D8)>4,1,0) -> 0
A9: Материалы о проведенном докинге/программном прогнозировании для выбора кандидатных молекул в отчете о НИР | D9: FALSE | E9: =IF(LEN(D9)>4,1,0) -> 0
A10: Публикация о механизмах возникновения заболевания | D10: FALSE | E10: =IF(LEN(D10)>4,1,0) -> 0
A11: Публикация о молекулярных мишенях | D11: FALSE | E11: =IF(LEN(D11)>4,1,0) -> 0
A12: Публикация о проведенном докинге/программном прогнозировании для выбора кандидатных молекул | D12: FALSE | E12: =IF(LEN(D12)>4,1,0) -> 0
A13: Монография о механизмах возникновения заболевания/ молекулярных мишенях/ проведенном докинге/программном прогнозировании для выбора кандидатных молекул | D13: FALSE | E13: =IF(LEN(D13)>4,1,0) -> 0
A14: Экспертное заключение о возможности разработки лекарственного средства | D14: FALSE | E14: =IF(LEN(D14)>4,1,0) -> 0
A15: Пояснительная записка о возможности разработки лекарственного средства | D15: FALSE | E15: =IF(LEN(D15)>4,1,0) -> 0
A16: Презентация о механизмах возникновения заболевания/ молекулярных мишенях/ проведенном докинге/программном прогнозировании для выбора кандидатных молекул | D16: FALSE | E16: =IF(LEN(D16)>4,1,0) -> 0
A17: Отчет о патентных исследованиях | D17: FALSE | E17: =IF(LEN(D17)>4,1,0) -> 0
A18: Материалы о методах синтеза в отчете о НИР | D18: FALSE | E18: =IF(LEN(D18)>4,1,0) -> 0
... A58: Отчеты клинических исследований (КИ II фазы) | D58: FALSE | E58: =IF(LEN(D58)>4,1,0) -> 0
E59: =SUM(E7:E58) -> 0

Sheet Р3_ДОК_ЛП
A1: Вернуться на главную страницу
A2: Перечень информационных материалов
A3: Вид результата: | C3: =Форма!B12 -> Прочее
A4: Тип результата: | C4: =Форма!C12 -> Иное
A6: Отметьте все информационные материалы, которые, по Вашей оценке, имеются в отчетной документации о результатах НИР
A7: Материалы о механизмах возникновения заболевания в отчете о НИР | D7: FALSE | E7: =IF(LEN(D7)>4,1,0) -> 0
A8: Материалы о молекулярных мишенях в отчете о НИР | D8: FALSE | E8: =IF(LEN(D8)>4,1,0) -> 0
A9: Материалы о проведенном докинге/программном прогнозировании для выбора кандидатных молекул в отчете о НИР | D9: FALSE | E9: =IF(LEN(D9)>4,1,0) -> 0
A10: Публикация о механизмах возникновения заболевания | D10: FALSE | E10: =IF(LEN(D10)>4,1,0) -> 0
A11: Публикация о молекулярных мишенях | D11: FALSE | E11: =IF(LEN(D11)>4,1,0) -> 0
A12: Публикация о проведенном докинге/программном прогнозировании для выбора кандидатных молекул | D12: FALSE | E12: =IF(LEN(D12)>4,1,0) -> 0
A13: Монография о механизмах возникновения заболевания/ молекулярных мишенях/ проведенном докинге/программном прогнозировании для выбора кандидатных молекул | D13: FALSE | E13: =IF(LEN(D13)>4,1,0) -> 0
A14: Экспертное заключение о возможности разработки лекарственного средства | D14: FALSE | E14: =IF(LEN(D14)>4,1,0) -> 0
A15: Пояснительная записка о возможности разработки лекарственного средства | D15: FALSE | E15: =IF(LEN(D15)>4,1,0) -> 0
A16: Презентация о механизмах возникновения заболевания/ молекулярных мишенях/ проведенном докинге/программном прогнозировании для выбора кандидатных молекул | D16: FALSE | E16: =IF(LEN(D16)>4,1,0) -> 0
A17: Отчет о патентных исследованиях | D17: FALSE | E17: =IF(LEN(D17)>4,1,0) -> 0
A18: Материалы о методах синтеза в отчете о НИР | D18: FALSE | E18: =IF(LEN(D18)>4,1,0) -> 0
... A58: Отчеты клинических исследований (КИ II фазы) | D58: FALSE | E58: =IF(LEN(D58)>4,1,0) -> 0
E59: =SUM(E7:E58) -> 0

Sheet Р1_ДОК_МИ
A1: Вернуться на главную страницу
A2: Перечень информационных материалов
A3: Вид результата: | C3: =Форма!B10 -> Метод профилактики
A4: Тип результата: | C4: =Форма!C10 -> Клинические рекомендации
A6: Отметьте все информационные материалы, которые, по Вашей оценке, имеются в отчетной документации о результатах НИР
A7: Материалы (обзор) о заболевании/механизмах возникновения заболевания в отчете о НИР | D7: FALSE | E7: =IF(LEN(D7)>4,1,0) -> 0
A8: Материалы (обзор) методик диагностики/лечения/профилактики заболевания в отчете о НИР | D8: FALSE | E8: =IF(LEN(D8)>4,1,0) -> 0
A9: Материалы о выборе методики диагностики (лечения или профилактики) в отчете о НИР | D9: FALSE | E9: =IF(LEN(D9)>4,1,0) -> 0
A10: Презентация о заболевании/механизмах возникновения заболевания, методиках диагностики/лечения/профилактики заболевания | D10: FALSE | E10: =IF(LEN(D10)>4,1,0) -> 0
A11: Отчет о патентных исследованиях | D11: FALSE | E11: =IF(LEN(D11)>4,1,0) -> 0
A12: Публикация (литературный или аналитический обзор) о заболевании/механизмах возникновения заболевания, методиках диагностики/лечения/профилактики заболевания | D12: FALSE | E12: =IF(LEN(D12)>4,1,0) -> 0
A13: Монография о заболевании/механизмах возникновения заболевания, методиках диагностики/лечения/профилактики заболевания | D13: FALSE | E13: =IF(LEN(D13)>4,1,0) -> 0
A14: Пояснительная записка о возможности разработки медицинского изделия | D14: FALSE | E14: =IF(LEN(D14)>4,1,0) -> 0
A15: Экспертное заключение о возможности разработки медицинского изделия | D15: FALSE | E15: =IF(LEN(D15)>4,1,0) -> 0
A16: Материалы в отчете о НИР о разработке, апробации и оптимизации методики диагностики (лечения или профилактики) | D16: FALSE | E16: =IF(LEN(D16)>4,1,0) -> 0
A17: Лабораторная технология получения элементов разрабатываемого медицинского изделия в отчете о НИР | D17: FALSE | E17: =IF(LEN(D17)>4,1,0) -> 0
A18: Описание принципа метода или принципа действия медицинского изделия в отчете о НИР | D18: FALSE | E18: =IF(LEN(D18)>4,1,0) -> 0
... A43: Заявление о государственной регистрации медицинского изделия с документами, указанным в Правилах регистрации медицинского изделия | D43: FALSE | E43: =IF(LEN(D43)>4,1,0) -> 0
E44: =SUM(E7:E43) -> 0

Sheet Р2_ДОК_МИ
A1: Вернуться на главную страницу
A2: Перечень информационных материалов
A3: Вид результата: | C3: =Форма!B11 -> Метод диагностики
A4: Тип результата: | C4: =Форма!C11 -> Клинические рекомендации
A6: Отметьте все информационные материалы, которые, по Вашей оценке, имеются в отчетной документации о результатах НИР
A7: Материалы (обзор) о заболевании/механизмах возникновения заболевания в отчете о НИР | D7: FALSE | E7: =IF(LEN(D7)>4,1,0) -> 0
A8: Материалы (обзор) методик диагностики/лечения/профилактики заболевания в отчете о НИР | D8: FALSE | E8: =IF(LEN(D8)>4,1,0) -> 0
A9: Материалы о выборе методики диагностики (лечения или профилактики) в отчете о НИР | D9: FALSE | E9: =IF(LEN(D9)>4,1,0) -> 0
A10: Презентация о заболевании/механизмах возникновения заболевания, методиках диагностики/лечения/профилактики заболевания | D10: FALSE | E10: =IF(LEN(D10)>4,1,0) -> 0
A11: Отчет о патентных исследованиях | D11: FALSE | E11: =IF(LEN(D11)>4,1,0) -> 0
A12: Публикация (литературный или аналитический обзор) о заболевании/механизмах возникновения заболевания, методиках диагностики/лечения/профилактики заболевания | D12: FALSE | E12: =IF(LEN(D12)>4,1,0) -> 0
A13: Монография о заболевании/механизмах возникновения заболевания, методиках диагностики/лечения/профилактики заболевания | D13: FALSE | E13: =IF(LEN(D13)>4,1,0) -> 0
A14: Пояснительная записка о возможности разработки медицинского изделия | D14: FALSE | E14: =IF(LEN(D14)>4,1,0) -> 0
A15: Экспертное заключение о возможности разработки медицинского изделия | D15: FALSE | E15: =IF(LEN(D15)>4,1,0) -> 0
A16: Материалы в отчете о НИР о разработке, апробации и оптимизации методики диагностики (лечения или профилактики) | D16: FALSE | E16: =IF(LEN(D16)>4,1,0) -> 0
A17: Лабораторная технология получения элементов разрабатываемого медицинского изделия в отчете о НИР | D17: FALSE | E17: =IF(LEN(D17)>4,1,0) -> 0
A18: Описание принципа метода или принципа действия медицинского изделия в отчете о НИР | D18: FALSE | E18: =IF(LEN(D18)>4,1,0) -> 0
... A43: Заявление о государственной регистрации медицинского изделия с документами, указанным в Правилах регистрации медицинского изделия | D43: FALSE | E43: =IF(LEN(D43)>4,1,0) -> 0
E44: =SUM(E7:E43) -> 0

Sheet Р3_ДОК_МИ
A1: Вернуться на главную страницу
A2: Перечень информационных материалов
A3: Вид результата: | C3: =Форма!B12 -> Прочее
A4: Тип результата: | C4: =Форма!C12 -> Иное
A6: Отметьте все информационные материалы, которые, по Вашей оценке, имеются в отчетной документации о результатах НИР
A7: Материалы (обзор) о заболевании/механизмах возникновения заболевания в отчете о НИР | D7: FALSE | E7: =IF(LEN(D7)>4,1,0) -> 0
A8: Материалы (обзор) методик диагностики/лечения/профилактики заболевания в отчете о НИР | D8: FALSE | E8: =IF(LEN(D8)>4,1,0) -> 0
A9: Материалы о выборе методики диагностики (лечения или профилактики) в отчете о НИР | D9: FALSE | E9: =IF(LEN(D9)>4,1,0) -> 0
A10: Презентация о заболевании/механизмах возникновения заболевания, методиках диагностики/лечения/профилактики заболевания | D10: FALSE | E10: =IF(LEN(D10)>4,1,0) -> 0
A11: Отчет о патентных исследованиях | D11: FALSE | E11: =IF(LEN(D11)>4,1,0) -> 0
A12: Публикация (литературный или аналитический обзор) о заболевании/механизмах возникновения заболевания, методиках диагностики/лечения/профилактики заболевания | D12: FALSE | E12: =IF(LEN(D12)>4,1,0) -> 0
A13: Монография о заболевании/механизмах возникновения заболевания, методиках диагностики/лечения/профилактики заболевания | D13: FALSE | E13: =IF(LEN(D13)>4,1,0) -> 0
A14: Пояснительная записка о возможности разработки медицинского изделия | D14: FALSE | E14: =IF(LEN(D14)>4,1,0) -> 0
A15: Экспертное заключение о возможности разработки медицинского изделия | D15: FALSE | E15: =IF(LEN(D15)>4,1,0) -> 0
A16: Материалы в отчете о НИР о разработке, апробации и оптимизации методики диагностики (лечения или профилактики) | D16: FALSE | E16: =IF(LEN(D16)>4,1,0) -> 0
A17: Лабораторная технология получения элементов разрабатываемого медицинского изделия в отчете о НИР | D17: FALSE | E17: =IF(LEN(D17)>4,1,0) -> 0
A18: Описание принципа метода или принципа действия медицинского изделия в отчете о НИР | D18: FALSE | E18: =IF(LEN(D18)>4,1,0) -> 0
... A43: Заявление о государственной регистрации медицинского изделия с документами, указанным в Правилах регистрации медицинского изделия | D43: FALSE | E43: =IF(LEN(D43)>4,1,0) -> 0
E44: =SUM(E7:E43) -> 0

Sheet Р1_ДОК_КР
A1: Вернуться на главную страницу
A2: Перечень информационных материалов
A3: Вид результата: | C3: =Форма!B10 -> Метод профилактики
A4: Тип результата: | C4: =Форма!C10 -> Клинические рекомендации
A6: Отметьте все информационные материалы, которые, по Вашей оценке, имеются в отчетной документации о результатах НИР
A7: Отчет о НИР, содержащий: - материалы о заболевании или состоянии (группе заболеваний или состояниях); - этиология и патогенез, эпидемиология, классификация, клиническая картина. | D7: FALSE | E7: =IF(LEN(D7)>4,1,0) -> 0
A8: Медико-экономическое обоснование разработки методов диагностики/лечения/реабилитации/профилактики для включения в клинические рекомендации | D8: FALSE | E8: =IF(LEN(D8)>4,1,0) -> 0
A9: Презентация | D9: FALSE | E9: =IF(LEN(D9)>4,1,0) -> 0
A10: Отчет о патентных исследованиях | D10: FALSE | E10: =IF(LEN(D10)>4,1,0) -> 0
A11: Публикация, содержащая экспериментальные данные, о разработке методов диагностики/лечения/реабилитации/профилактики | D11: FALSE | E11: =IF(LEN(D11)>4,1,0) -> 0
A12: Пояснительная записка | D12: FALSE | E12: =IF(LEN(D12)>4,1,0) -> 0
A13: Экспертное заключение | D13: FALSE | E13: =IF(LEN(D13)>4,1,0) -> 0
A14: Монография, содержащая экспериментальные данные о разработке методов диагностики/лечения/реабилитации/профилактики | D14: FALSE | E14: =IF(LEN(D14)>4,1,0) -> 0
A15: Отчет о НИР, включающий: - материалы о целевых областях применения методов диагностики/лечения/реабилитации/профилактики | D15: TRUE | E15: =IF(LEN(D15)>4,1,0) -> 1
A16: Экспериментальные данные, подтверждающие работоспособность и применимость разрабатываемых методов | D16: TRUE | E16: =IF(LEN(D16)>4,1,0) -> 1
A17: Стандартизированный и (или) валидированный и (или) верифицированный: - метод диагностики; - метод лечения; - метод реабилитации; -метод профилактики | D17: TRUE | E17: =IF(LEN(D17)>4,1,0) -> 1
A18: Проект технического задания на разработку активной фармацевтической субстанции (АФС) и готовой лекарственной формы (ГЛФ) | D18: FALSE | E18: =IF(LEN(D18)>4,1,0) -> 0
... A32: Доработанный проект клинических рекомендаций | D32: FALSE | E32: =IF(LEN(D32)>4,1,0) -> 0
E33: =SUM(E7:E32) -> 6

Sheet Р2_ДОК_КР
A1: Вернуться на главную страницу
A2: Перечень информационных материалов
A3: Вид результата: | C3: =Форма!B11 -> Метод диагностики
A4: Тип результата: | C4: =Форма!C11 -> Клинические рекомендации
A6: Отметьте все информационные материалы, которые, по Вашей оценке, имеются в отчетной документации о результатах НИР
A7: Отчет о НИР, содержащий: - материалы о заболевании или состоянии (группе заболеваний или состояниях); - этиология и патогенез, эпидемиология, классификация, клиническая картина. | D7: FALSE | E7: =IF(LEN(D7)>4,1,0) -> 0
A8: Медико-экономическое обоснование разработки методов диагностики/лечения/реабилитации/профилактики для включения в клинические рекомендации | D8: FALSE | E8: =IF(LEN(D8)>4,1,0) -> 0
A9: Презентация | D9: FALSE | E9: =IF(LEN(D9)>4,1,0) -> 0
A10: Отчет о патентных исследованиях | D10: FALSE | E10: =IF(LEN(D10)>4,1,0) -> 0
A11: Публикация, содержащая экспериментальные данные, о разработке методов диагностики/лечения/реабилитации/профилактики | D11: FALSE | E11: =IF(LEN(D11)>4,1,0) -> 0
A12: Пояснительная записка | D12: FALSE | E12: =IF(LEN(D12)>4,1,0) -> 0
A13: Экспертное заключение | D13: FALSE | E13: =IF(LEN(D13)>4,1,0) -> 0
A14: Монография, содержащая экспериментальные данные о разработке методов диагностики/лечения/реабилитации/профилактики | D14: FALSE | E14: =IF(LEN(D14)>4,1,0) -> 0
A15: Отчет о НИР, включающий: - материалы о целевых областях применения методов диагностики/лечения/реабилитации/профилактики | D15: TRUE | E15: =IF(LEN(D15)>4,1,0) -> 1
A16: Экспериментальные данные, подтверждающие работоспособность и применимость разрабатываемых методов | D16: TRUE | E16: =IF(LEN(D16)>4,1,0) -> 1
A17: Стандартизированный и (или) валидированный и (или) верифицированный: - метод диагностики; - метод лечения; - метод реабилитации; -метод профилактики | D17: TRUE | E17: =IF(LEN(D17)>4,1,0) -> 1
A18: Проект технического задания на разработку активной фармацевтической субстанции (АФС) и готовой лекарственной формы (ГЛФ) | D18: FALSE | E18: =IF(LEN(D18)>4,1,0) -> 0
... A32: Доработанный проект клинических рекомендаций | D32: FALSE | E32: =IF(LEN(D32)>4,1,0) -> 0
E33: =SUM(E7:E32) -> 6

Sheet Р3_ДОК_КР
A1: Вернуться на главную страницу
A2: Перечень информационных материалов
A3: Вид результата: | C3: =Форма!B12 -> Прочее
A4: Тип результата: | C4: =Форма!C12 -> Иное
A6: Отметьте все информационные материалы, которые, по Вашей оценке, имеются в отчетной документации о результатах НИР
A7: Отчет о НИР, содержащий: - материалы о заболевании или состоянии (группе заболеваний или состояниях); - этиология и патогенез, эпидемиология, классификация, клиническая картина. | D7: FALSE | E7: =IF(LEN(D7)>4,1,0) -> 0
A8: Медико-экономическое обоснование разработки методов диагностики/лечения/реабилитации/профилактики для включения в клинические рекомендации | D8: FALSE | E8: =IF(LEN(D8)>4,1,0) -> 0
A9: Презентация | D9: FALSE | E9: =IF(LEN(D9)>4,1,0) -> 0
A10: Отчет о патентных исследованиях | D10: FALSE | E10: =IF(LEN(D10)>4,1,0) -> 0
A11: Публикация, содержащая экспериментальные данные, о разработке методов диагностики/лечения/реабилитации/профилактики | D11: FALSE | E11: =IF(LEN(D11)>4,1,0) -> 0
A12: Пояснительная записка | D12: FALSE | E12: =IF(LEN(D12)>4,1,0) -> 0
A13: Экспертное заключение | D13: FALSE | E13: =IF(LEN(D13)>4,1,0) -> 0
A14: Монография, содержащая экспериментальные данные о разработке методов диагностики/лечения/реабилитации/профилактики | D14: FALSE | E14: =IF(LEN(D14)>4,1,0) -> 0
A15: Отчет о НИР, включающий: - материалы о целевых областях применения методов диагностики/лечения/реабилитации/профилактики | D15: FALSE | E15: =IF(LEN(D15)>4,1,0) -> 0
A16: Экспериментальные данные, подтверждающие работоспособность и применимость разрабатываемых методов | D16: FALSE | E16: =IF(LEN(D16)>4,1,0) -> 0
A17: Стандартизированный и (или) валидированный и (или) верифицированный: - метод диагностики; - метод лечения; - метод реабилитации; -метод профилактики | D17: FALSE | E17: =IF(LEN(D17)>4,1,0) -> 0
A18: Проект технического задания на разработку активной фармацевтической субстанции (АФС) и готовой лекарственной формы (ГЛФ) | D18: FALSE | E18: =IF(LEN(D18)>4,1,0) -> 0
... A32: Доработанный проект клинических рекомендаций | D32: FALSE | E32: =IF(LEN(D32)>4,1,0) -> 0
E33: =SUM(E7:E32) -> 0

Sheet Р1_ДОК_Иное
A1: Вернуться на главную страницу
A2: Перечень информационных материалов
A3: Вид результата: | C3: =Форма!B10 -> Метод профилактики
A4: Тип результата: | C4: =Форма!C10 -> Клинические рекомендации
A6: Отметьте все информационные материалы, которые, по Вашей оценке, имеются в отчетной документации о результатах НИР
A7: Аналитическая записка | D7: FALSE | E7: =IF(LEN(D7)>4,1,0) -> 0
A8: Пояснительная записка | D8: FALSE | E8: =IF(LEN(D8)>4,1,0) -> 0
A9: Презентация | D9: FALSE | E9: =IF(LEN(D9)>4,1,0) -> 0
A10: Материалы в отчете о научно-исследовательской работе | D10: FALSE | E10: =IF(LEN(D10)>4,1,0) -> 0
A11: Справка | D11: FALSE | E11: =IF(LEN(D11)>4,1,0) -> 0
A12: Экспертное заключение | D12: FALSE | E12: =IF(LEN(D12)>4,1,0) -> 0
A13: Монография | D13: FALSE | E13: =IF(LEN(D13)>4,1,0) -> 0
A14: Публикация | D14: FALSE | E14: =IF(LEN(D14)>4,1,0) -> 0
E15: =SUM(E7:E14) -> 0

Sheet Р2_ДОК_Иное
A1: Вернуться на главную страницу
A2: Перечень информационных материалов
A3: Вид результата: | C3: =Форма!B11 -> Метод диагностики
A4: Тип результата: | C4: =Форма!C11 -> Клинические рекомендации
A6: Отметьте все информационные материалы, которые, по Вашей оценке, имеются в отчетной документации о результатах НИР
A7: Аналитическая записка | D7: FALSE | E7: =IF(LEN(D7)>4,1,0) -> 0
A8: Пояснительная записка | D8: FALSE | E8: =IF(LEN(D8)>4,1,0) -> 0
A9: Презентация | D9: FALSE | E9: =IF(LEN(D9)>4,1,0) -> 0
A10: Материалы в отчете о научно-исследовательской работе | D10: FALSE | E10: =IF(LEN(D10)>4,1,0) -> 0
A11: Справка | D11: FALSE | E11: =IF(LEN(D11)>4,1,0) -> 0
A12: Экспертное заключение | D12: FALSE | E12: =IF(LEN(D12)>4,1,0) -> 0
A13: Монография | D13: FALSE | E13: =IF(LEN(D13)>4,1,0) -> 0
A14: Публикация | D14: FALSE | E14: =IF(LEN(D14)>4,1,0) -> 0
E15: =SUM(E7:E14) -> 0

Sheet Р3_ДОК_Иное
A1: Вернуться на главную страницу
A2: Перечень информационных материалов
A3: Вид результата: | C3: =Форма!B12 -> Прочее
A4: Тип результата: | C4: =Форма!C12 -> Иное
A6: Отметьте все информационные материалы, которые, по Вашей оценке, имеются в отчетной документации о результатах НИР
A7: Аналитическая записка | D7: FALSE | E7: =IF(LEN(D7)>4,1,0) -> 0
A8: Пояснительная записка | D8: FALSE | E8: =IF(LEN(D8)>4,1,0) -> 0
A9: Презентация | D9: FALSE | E9: =IF(LEN(D9)>4,1,0) -> 0
A10: Материалы в отчете о научно-исследовательской работе | D10: TRUE | E10: =IF(LEN(D10)>4,1,0) -> 1
A11: Справка | D11: FALSE | E11: =IF(LEN(D11)>4,1,0) -> 0
A12: Экспертное заключение | D12: FALSE | E12: =IF(LEN(D12)>4,1,0) -> 0
A13: Монография | D13: TRUE | E13: =IF(LEN(D13)>4,1,0) -> 1
A14: Публикация | D14: TRUE | E14: =IF(LEN(D14)>4,1,0) -> 1
E15: =SUM(E7:E14) -> 3

Sheet Р1_КТ
A1: Вернуться на главную страницу
A2: Перечень критических технологий
A3: Вид результата: | C3: =Форма!B10 -> Метод профилактики
A4: Тип результата: | C4: =Форма!C10 -> Клинические рекомендации
A6: Отметьте критические технгологии, к которым, по Вашей оценке, относится результат НИР
A7: Биомедицинские и когнитивные технологии здорового и активного долголетия | D7: TRUE | E7: =IF(LEN(D7)>4,1,0) -> 1
A8: Технологии разработки лекарственных средств и платформ нового поколения (биотехнологических, высокотехнологичных и радиофармацевтических лекарственных препаратов) | D8: FALSE | E8: =IF(LEN(D8)>4,1,0) -> 0
A9: Технологии персонализированного, лечебного и функционального питания для здоровьесбережения | D9: FALSE | E9: =IF(LEN(D9)>4,1,0) -> 0
A10: Технологии разработки медицинских изделий нового поколения, включая биогибридные, бионические технологии и нейротехнологии | D10: FALSE | E10: =IF(LEN(D10)>4,1,0) -> 0
E11: =SUM(E7:E10) -> 1

Sheet Р2_КТ
A1: Вернуться на главную страницу
A2: Перечень критических технологий
A3: Вид результата: | C3: =Форма!B11 -> Метод диагностики
A4: Тип результата: | C4: =Форма!C11 -> Клинические рекомендации
A6: Отметьте критические технгологии, к которым, по Вашей оценке, относится результат НИР
A7: Биомедицинские и когнитивные технологии здорового и активного долголетия | D7: TRUE | E7: =IF(LEN(D7)>4,1,0) -> 1
A8: Технологии разработки лекарственных средств и платформ нового поколения (биотехнологических, высокотехнологичных и радиофармацевтических лекарственных препаратов) | D8: FALSE | E8: =IF(LEN(D8)>4,1,0) -> 0
A9: Технологии персонализированного, лечебного и функционального питания для здоровьесбережения | D9: FALSE | E9: =IF(LEN(D9)>4,1,0) -> 0
A10: Технологии разработки медицинских изделий нового поколения, включая биогибридные, бионические технологии и нейротехнологии | D10: FALSE | E10: =IF(LEN(D10)>4,1,0) -> 0
E11: =SUM(E7:E10) -> 1

Sheet Р3_КТ
A1: Вернуться на главную страницу
A2: Перечень критических технологий
A3: Вид результата: | C3: =Форма!B12 -> Прочее
A4: Тип результата: | C4: =Форма!C12 -> Иное
A6: Отметьте критические технгологии, к которым, по Вашей оценке, относится результат НИР
A7: Биомедицинские и когнитивные технологии здорового и активного долголетия | D7: TRUE | E7: =IF(LEN(D7)>4,1,0) -> 1
A8: Технологии разработки лекарственных средств и платформ нового поколения (биотехнологических, высокотехнологичных и радиофармацевтических лекарственных препаратов) | D8: FALSE | E8: =IF(LEN(D8)>4,1,0) -> 0
A9: Технологии персонализированного, лечебного и функционального питания для здоровьесбережения | D9: FALSE | E9: =IF(LEN(D9)>4,1,0) -> 0
A10: Технологии разработки медицинских изделий нового поколения, включая биогибридные, бионические технологии и нейротехнологии | D10: FALSE | E10: =IF(LEN(D10)>4,1,0) -> 0
E11: =SUM(E7:E10) -> 1

Sheet Р1_СТ
A1: Вернуться на главную страницу
A2: Перечень сквозных технологий
A3: Вид результата: | C3: =Форма!B10 -> Метод профилактики
A4: Тип результата: | C4: =Форма!C10 -> Клинические рекомендации
A6: Отметьте сквозные технгологии, к которым, по Вашей оценке, относится результат НИР
A7: Технологии, основанные на методах синтетической биологии и генной инженерии | D7: FALSE | E7: =IF(LEN(D7)>4,1,0) -> 0
A8: Технологии создания новых материалов с заданными свойствами и эксплуатационными характеристиками | D8: FALSE | E8: =IF(LEN(D8)>4,1,0) -> 0
A9: Технологии производства малотоннажной химической продукции, включая особо чистые вещества, для фармацевтики, энергетики и микроэлектроники | D9: FALSE | E9: =IF(LEN(D9)>4,1,0) -> 0
A10: Биотехнологии в отраслях экономики | D10: TRUE | E10: =IF(LEN(D10)>4,1,0) -> 1
E11: =SUM(E7:E10) -> 1

Sheet Р2_СТ
A1: Вернуться на главную страницу
A2: Перечень сквозных технологий
A3: Вид результата: | C3: =Форма!B11 -> Метод диагностики
A4: Тип результата: | C4: =Форма!C11 -> Клинические рекомендации
A6: Отметьте сквозные технгологии, к которым, по Вашей оценке, относится результат НИР
A7: Технологии, основанные на методах синтетической биологии и генной инженерии | D7: FALSE | E7: =IF(LEN(D7)>4,1,0) -> 0
A8: Технологии создания новых материалов с заданными свойствами и эксплуатационными характеристиками | D8: FALSE | E8: =IF(LEN(D8)>4,1,0) -> 0
A9: Технологии производства малотоннажной химической продукции, включая особо чистые вещества, для фармацевтики, энергетики и микроэлектроники | D9: FALSE | E9: =IF(LEN(D9)>4,1,0) -> 0
A10: Биотехнологии в отраслях экономики | D10: TRUE | E10: =IF(LEN(D10)>4,1,0) -> 1
E11: =SUM(E7:E10) -> 1

Sheet Р3_СТ
A1: Вернуться на главную страницу
A2: Перечень сквозных технологий
A3: Вид результата: | C3: =Форма!B12 -> Прочее
A4: Тип результата: | C4: =Форма!C12 -> Иное
A6: Отметьте сквозные технгологии, к которым, по Вашей оценке, относится результат НИР
A7: Технологии, основанные на методах синтетической биологии и генной инженерии | D7: FALSE | E7: =IF(LEN(D7)>4,1,0) -> 0
A8: Технологии создания новых материалов с заданными свойствами и эксплуатационными характеристиками | D8: FALSE | E8: =IF(LEN(D8)>4,1,0) -> 0
A9: Технологии производства малотоннажной химической продукции, включая особо чистые вещества, для фармацевтики, энергетики и микроэлектроники | D9: FALSE | E9: =IF(LEN(D9)>4,1,0) -> 0
A10: Биотехнологии в отраслях экономики | D10: TRUE | E10: =IF(LEN(D10)>4,1,0) -> 1
E11: =SUM(E7:E10) -> 1

Sheet Р1_НИОКТР_1
A1: Вернуться на главную страницу
A2: Основа для выполнения последующих НИОКТР в период 2026-2030 гг.
A3: Вид результата: | C3: =Форма!B10 -> Метод профилактики
A4: Тип результата: | C4: =Форма!C10 -> Клинические рекомендации
A6: Могут ли научные результаты, полученные при выполнении научно-исследовательской работы, при наличии финансирования стать основой для последующих НИОКТР с достижением следующих результатов* в интервале времени 2026-2030 годы
E7: =LEN(A7) -> 0
A8: выберите ответ ­
A9: * | B9: Разработаны новые медицинские технологии, лекарственные средства, медицинские изделия, на базе нейротехнологий, направленные на предупреждение и лечение когнитивных и сенсорных нарушений
B10: Разработаны (зарегистрированы) новые медицинские изделия (оборудование), основанные на биопечати, и медицинские технологии, связанные с их применением
B11: Разработаны и внедрены индивидуальные (под конкретного пациента) лекарственные препараты, в том числе с использованием генетических технологий
B12: Проведены клинические исследования лекарственных препаратов и медицинских изделий, направленных на снижение бремени возраст-ассоциированных заболеваний
B13: Проведены исследования, направленные на оценку процессов старения клеток и выявления причин старения
B14: Разработаны технологии, направленные на диагностику биологического возраста, включая разработку и внедрение новых тест-систем, и его коррекцию
B15: Разработаны технологии превентивной медицины и здорового питания для внедрения медицинскими подразделениями медицинской профилактики (центрами здоровья)

Sheet Р2_НИОКТР_1
A1: Вернуться на главную страницу
A2: Основа для выполнения последующих НИОКТР в период 2026-2030 гг.
A3: Вид результата: | C3: =Форма!B11 -> Метод диагностики
A4: Тип результата: | C4: =Форма!C11 -> Клинические рекомендации
A6: Могут ли научные результаты, полученные при выполнении научно-исследовательской работы, при наличии финансирования стать основой для последующих НИОКТР с достижением следующих результатов* в интервале времени 2026-2030 годы
E7: =LEN(A7) -> 0
A8: выберите ответ ­
A9: * | B9: Разработаны новые медицинские технологии, лекарственные средства, медицинские изделия, на базе нейротехнологий, направленные на предупреждение и лечение когнитивных и сенсорных нарушений
B10: Разработаны (зарегистрированы) новые медицинские изделия (оборудование), основанные на биопечати, и медицинские технологии, связанные с их применением
B11: Разработаны и внедрены индивидуальные (под конкретного пациента) лекарственные препараты, в том числе с использованием генетических технологий
B12: Проведены клинические исследования лекарственных препаратов и медицинских изделий, направленных на снижение бремени возраст-ассоциированных заболеваний
B13: Проведены исследования, направленные на оценку процессов старения клеток и выявления причин старения
B14: Разработаны технологии, направленные на диагностику биологического возраста, включая разработку и внедрение новых тест-систем, и его коррекцию
B15: Разработаны технологии превентивной медицины и здорового питания для внедрения медицинскими подразделениями медицинской профилактики (центрами здоровья)

Sheet Р3_НИОКТР_1
A1: Вернуться на главную страницу
A2: Основа для выполнения последующих НИОКТР в период 2026-2030 гг.
A3: Вид результата: | C3: =Форма!B12 -> Прочее
A4: Тип результата: | C4: =Форма!C12 -> Иное
A6: Могут ли научные результаты, полученные при выполнении научно-исследовательской работы, при наличии финансирования стать основой для последующих НИОКТР с достижением следующих результатов* в интервале времени 2026-2030 годы
E7: =LEN(A7) -> 0
A8: выберите ответ ­
A9: * | B9: Разработаны новые медицинские технологии, лекарственные средства, медицинские изделия, на базе нейротехнологий, направленные на предупреждение и лечение когнитивных и сенсорных нарушений
B10: Разработаны (зарегистрированы) новые медицинские изделия (оборудование), основанные на биопечати, и медицинские технологии, связанные с их применением
B11: Разработаны и внедрены индивидуальные (под конкретного пациента) лекарственные препараты, в том числе с использованием генетических технологий
B12: Проведены клинические исследования лекарственных препаратов и медицинских изделий, направленных на снижение бремени возраст-ассоциированных заболеваний
B13: Проведены исследования, направленные на оценку процессов старения клеток и выявления причин старения
B14: Разработаны технологии, направленные на диагностику биологического возраста, включая разработку и внедрение новых тест-систем, и его коррекцию
B15: Разработаны технологии превентивной медицины и здорового питания для внедрения медицинскими подразделениями медицинской профилактики (центрами здоровья)

Sheet ВР
A1: Перечень типов результатов тематик научных исследований в интересах медицины и здравоохранения
A2: Код результата | B2: Тип результата | D2: Лекарственный препарат (средство) | E2: Мишень для терапии | F2: Модель заболевания | G2: Медицинское изделие | H2: Новый материал | I2: Тест-система | J2: Набор реагентов | K2: Метод диагностики | L2: Метод лечения | M2: Метод профилактики | N2: Метод реабилитации | O2: Метод прогнозирования | P2: Новые знания о предмете исследования (орган, клетка, молекула, геном) | Q2: Выводы (рекомендации) для принятия управленческих решений на основании популяционных данных, эпидемиологических данных | R2: Прочее
A3: Р1 | B3: лекарственный препарат (средство) | D3: Лекарственный препарат | E3: Лекарственный препарат | F3: Лекарственный препарат | G3: Медицинское изделие | H3: Медицинское изделие | I3: Медицинское изделие | J3: Медицинское изделие | K3: Клинические рекомендации | L3: Клинические рекомендации | M3: Клинические рекомендации | N3: Клинические рекомендации | O3: Клинические рекомендации | P3: Иное | Q3: Иное | R3: Иное
A4: Р2 | B4: мишень для терапии | F4: Медицинское изделие
A5: Р3 | B5: модель заболевания
A6: Р4 | B6: медицинское изделие
A7: Р5 | B7: новый материал
A8: Р6 | B8: тест-система
A9: Р7 | B9: метод диагностики
A10: Р8 | B10: метод лечения
A11: Р9 | B11: метод профилактики
A12: Р10 | B12: метод реабилитации
A13: Р11 | B13: метод прогнозирования
A14: Р12 | B14: новые знания о предмете исследования (орган, клетка, молекула, геном)
A15: Р13 | B15: выводы (рекомендации) для принятия управленческих решений на основании популяционных данных, эпидемиологических данных
A16: Р14 | B16: иное (указать)

Sheet Соотв
A1: Number | B1: Conformity
A2: 1
A3: 2 | B3: Соответствует
A4: 3 | B4: Частично соответствует
A5: 4 | B5: Не соответствует

Sheet Р1_НИОКТР_2
A1: Вернуться на главную страницу
A2: Перечень ожидаемых результатов в интервале времени 2026-2030 годы
A3: Вид результата: | C3: =Форма!B10 -> Метод профилактики
A4: Тип результата: | C4: =Форма!C10 -> Клинические рекомендации
A6: Отметьте результаты, которые могут быть достигнуты в интервале 2026-2030 гг.
A7: Разработаны новые медицинские технологии, лекарственные средства, медицинские изделия, на базе нейротехнологий, направленные на предупреждение и лечение когнитивных и сенсорных нарушений | D7: FALSE | E7: =IF(LEN(D7)>4,1,0) -> 0
A8: Разработаны (зарегистрированы) новые медицинские изделия (оборудование), основанные на биопечати, и медицинские технологии, связанные с их применением | D8: FALSE | E8: =IF(LEN(D8)>4,1,0) -> 0
A9: Разработаны и внедрены индивидуальные (под конкретного пациента) лекарственные препараты, в том числе с использованием генетических технологий | D9: FALSE | E9: =IF(LEN(D9)>4,1,0) -> 0
A10: Проведены клинические исследования лекарственных препаратов и медицинских изделий, направленных на снижение бремени возраст-ассоциированных заболеваний | D10: FALSE | E10: =IF(LEN(D10)>4,1,0) -> 0
A11: Проведены исследования, направленные на оценку процессов старения клеток и выявления причин старения | D11: FALSE | E11: =IF(LEN(D11)>4,1,0) -> 0
A12: Разработаны технологии, направленные на диагностику биологического возраста, включая разработку и внедрение новых тест-систем, и его коррекцию | D12: FALSE | E12: =IF(LEN(D12)>4,1,0) -> 0
A13: Разработаны технологии превентивной медицины и здорового питания для внедрения медицинскими подразделениями медицинской профилактики (центрами здоровья) | D13: FALSE | E13: =IF(LEN(D13)>4,1,0) -> 0
E14: =SUM(E7:E13) -> 0

Sheet Р2_НИОКТР_2
A1: Вернуться на главную страницу
A2: Перечень ожидаемых результатов в интервале времени 2026-2030 годы
A3: Вид результата: | C3: =Форма!B11 -> Метод диагностики
A4: Тип результата: | C4: =Форма!C11 -> Клинические рекомендации
A6: Отметьте результаты, которые могут быть достигнуты в интервале 2026-2030 гг.
A7: Разработаны новые медицинские технологии, лекарственные средства, медицинские изделия, на базе нейротехнологий, направленные на предупреждение и лечение когнитивных и сенсорных нарушений | D7: FALSE | E7: =IF(LEN(D7)>4,1,0) -> 0
A8: Разработаны (зарегистрированы) новые медицинские изделия (оборудование), основанные на биопечати, и медицинские технологии, связанные с их применением | D8: FALSE | E8: =IF(LEN(D8)>4,1,0) -> 0
A9: Разработаны и внедрены индивидуальные (под конкретного пациента) лекарственные препараты, в том числе с использованием генетических технологий | D9: FALSE | E9: =IF(LEN(D9)>4,1,0) -> 0
A10: Проведены клинические исследования лекарственных препаратов и медицинских изделий, направленных на снижение бремени возраст-ассоциированных заболеваний | D10: FALSE | E10: =IF(LEN(D10)>4,1,0) -> 0
A11: Проведены исследования, направленные на оценку процессов старения клеток и выявления причин старения | D11: FALSE | E11: =IF(LEN(D11)>4,1,0) -> 0
A12: Разработаны технологии, направленные на диагностику биологического возраста, включая разработку и внедрение новых тест-систем, и его коррекцию | D12: FALSE | E12: =IF(LEN(D12)>4,1,0) -> 0
A13: Разработаны технологии превентивной медицины и здорового питания для внедрения медицинскими подразделениями медицинской профилактики (центрами здоровья) | D13: FALSE | E13: =IF(LEN(D13)>4,1,0) -> 0
E14: =SUM(E7:E13) -> 0

Sheet Р3_НИОКТР_2
A1: Вернуться на главную страницу
A2: Перечень ожидаемых результатов в интервале времени 2026-2030 годы
A3: Вид результата: | C3: =Форма!B12 -> Прочее
A4: Тип результата: | C4: =Форма!C12 -> Иное
A6: Отметьте результаты, которые могут быть достигнуты в интервале 2026-2030 гг.
A7: Разработаны новые медицинские технологии, лекарственные средства, медицинские изделия, на базе нейротехнологий, направленные на предупреждение и лечение когнитивных и сенсорных нарушений | D7: FALSE | E7: =IF(LEN(D7)>4,1,0) -> 0
A8: Разработаны (зарегистрированы) новые медицинские изделия (оборудование), основанные на биопечати, и медицинские технологии, связанные с их применением | D8: FALSE | E8: =IF(LEN(D8)>4,1,0) -> 0
A9: Разработаны и внедрены индивидуальные (под конкретного пациента) лекарственные препараты, в том числе с использованием генетических технологий | D9: FALSE | E9: =IF(LEN(D9)>4,1,0) -> 0
A10: Проведены клинические исследования лекарственных препаратов и медицинских изделий, направленных на снижение бремени возраст-ассоциированных заболеваний | D10: FALSE | E10: =IF(LEN(D10)>4,1,0) -> 0
A11: Проведены исследования, направленные на оценку процессов старения клеток и выявления причин старения | D11: FALSE | E11: =IF(LEN(D11)>4,1,0) -> 0
A12: Разработаны технологии, направленные на диагностику биологического возраста, включая разработку и внедрение новых тест-систем, и его коррекцию | D12: FALSE | E12: =IF(LEN(D12)>4,1,0) -> 0
A13: Разработаны технологии превентивной медицины и здорового питания для внедрения медицинскими подразделениями медицинской профилактики (центрами здоровья) | D13: FALSE | E13: =IF(LEN(D13)>4,1,0) -> 0
E14: =SUM(E7:E13) -> 0

Sheet НИОКТР_26-30
A1: Number | B1: Choice
A2: 0 | B2: Не выбран ни один вариант
A3: 1 | B3: Да, полученные научные результаты могут быть основой для последующих НИОКТР с достижением следующих результатов* в интервале времени 2026-2030 годы
A4: 2 | B4: Да, при условии существенной интенсификации научной работы возможно достижение следующих результатов* на основе полученных научных результатов в интервале времени 2026-2030 гг.
A5: 3 | B5: Нет, полученные научные результаты не относятся к указанным направлениям*
A6: 4 | B6: Нет, в интервал времени 2026-2030 достижение указанных результатов* невозможно на основе достигнутых результатов НИР

Sheet Баллы
A1: Оцените вклад результата НИР в ее решение в виде единственного выбора из числа приведенных вариантов.
A2: № | B2: Клинический эффект | C2: Возможность импортозамещения | D2: Баллы
A3: 1 | B3: Снижение смертности | C3: Имеется возможность серийного производства в России | D3: 10
C4: Отсутствует возможность серийного производства в России | D4: 9
A5: 2 | B5: Снижение инвалидизации в несовершеннолетнем возрасте (предотвращение инвалидности, достижение отсрочки в наступлении инвалидности, снятие инвалидности) | C5: Имеется возможность серийного производства в России | D5: 8
C6: Отсутствует возможность серийного производства в России | D6: 7
A7: 3 | B7: Снижение инвалидизации в совершеннолетнем возрасте (предотвращение инвалидности, достижение отсрочки в наступлении инвалидности, переход в менее тяжелую группу инвалидности, снятие инвалидности) | C7: Имеется возможность серийного производства в России | D7: 6
C8: Отсутствует возможность серийного производства в России | D8: 5
A9: 4 | B9: Снижение временной утраты трудоспособности (более 14 дней) | C9: Имеется возможность серийного производства в России | D9: 4
C10: Отсутствует возможность серийного производства в России | D10: 3
A11: 5 | B11: Снижение временной утраты трудоспособности (до 14 дней) | C11: Имеется возможность серийного производства в России | D11: 2
C12: Отсутствует возможность серийного производства в России | D12: 1
A13: 6 | B13: Повышение качества жизни, связанного с состоянием здоровья | C13: Имеется возможность серийного производства в России | D13: 2
C14: Отсутствует возможность серийного производства в России | D14: 1
